{
"meta":{"test_sets":[],"test_metrics":[],"learn_metrics":[{"best_value":"Min","name":"Logloss"}],"launch_mode":"Train","parameters":"","iteration_count":1000,"learn_sets":["learn"],"name":"experiment"},
"iterations":[
{"learn":[0.6388184988],"iteration":0,"passed_time":0.2130496318,"remaining_time":212.8365822},
{"learn":[0.5928833521],"iteration":1,"passed_time":0.4012533567,"remaining_time":200.225425},
{"learn":[0.5505707301],"iteration":2,"passed_time":0.5907059813,"remaining_time":196.3112878},
{"learn":[0.5127454538],"iteration":3,"passed_time":0.792444963,"remaining_time":197.3187958},
{"learn":[0.4793132709],"iteration":4,"passed_time":0.9888753207,"remaining_time":196.7861888},
{"learn":[0.4511888577],"iteration":5,"passed_time":1.17280308,"remaining_time":194.2943769},
{"learn":[0.4257305292],"iteration":6,"passed_time":1.369531612,"remaining_time":194.2778416},
{"learn":[0.4025025918],"iteration":7,"passed_time":1.549754627,"remaining_time":192.1695738},
{"learn":[0.3831962109],"iteration":8,"passed_time":1.735767892,"remaining_time":191.1273313},
{"learn":[0.3658371412],"iteration":9,"passed_time":1.916110984,"remaining_time":189.6949874},
{"learn":[0.3495794883],"iteration":10,"passed_time":2.101062459,"remaining_time":188.9046156},
{"learn":[0.3350144716],"iteration":11,"passed_time":2.28631448,"remaining_time":188.2398922},
{"learn":[0.3216896864],"iteration":12,"passed_time":2.485595544,"remaining_time":188.7140617},
{"learn":[0.309714266],"iteration":13,"passed_time":2.673167413,"remaining_time":188.2673621},
{"learn":[0.2989403578],"iteration":14,"passed_time":2.875356771,"remaining_time":188.8150946},
{"learn":[0.2893795747],"iteration":15,"passed_time":3.090907459,"remaining_time":190.0908087},
{"learn":[0.2809128505],"iteration":16,"passed_time":3.321743027,"remaining_time":192.0749056},
{"learn":[0.2733213168],"iteration":17,"passed_time":3.613052564,"remaining_time":197.1120899},
{"learn":[0.2672019665],"iteration":18,"passed_time":3.822730195,"remaining_time":197.3735959},
{"learn":[0.26058321],"iteration":19,"passed_time":4.040066437,"remaining_time":197.9632554},
{"learn":[0.2542881562],"iteration":20,"passed_time":4.27706724,"remaining_time":199.3928013},
{"learn":[0.2498719362],"iteration":21,"passed_time":4.593304536,"remaining_time":204.1932653},
{"learn":[0.2446953975],"iteration":22,"passed_time":4.816701547,"remaining_time":204.6051049},
{"learn":[0.2408010795],"iteration":23,"passed_time":5.057277092,"remaining_time":205.6626018},
{"learn":[0.2369729317],"iteration":24,"passed_time":5.275774666,"remaining_time":205.755212},
{"learn":[0.2323830531],"iteration":25,"passed_time":5.486411038,"remaining_time":205.5293981},
{"learn":[0.2285425131],"iteration":26,"passed_time":5.698051106,"remaining_time":205.3408788},
{"learn":[0.2244022975],"iteration":27,"passed_time":5.875670924,"remaining_time":203.9697192},
{"learn":[0.2209459635],"iteration":28,"passed_time":6.078488918,"remaining_time":203.5245772},
{"learn":[0.2175950692],"iteration":29,"passed_time":6.264030979,"remaining_time":202.5370017},
{"learn":[0.21437934],"iteration":30,"passed_time":6.462944794,"remaining_time":202.0191453},
{"learn":[0.2119408076],"iteration":31,"passed_time":6.667759545,"remaining_time":201.6997262},
{"learn":[0.2094557084],"iteration":32,"passed_time":6.857432495,"remaining_time":200.9435522},
{"learn":[0.2073169727],"iteration":33,"passed_time":7.054250276,"remaining_time":200.423699},
{"learn":[0.2043036681],"iteration":34,"passed_time":7.231598437,"remaining_time":199.3854998},
{"learn":[0.2016402941],"iteration":35,"passed_time":7.509633223,"remaining_time":201.0912896},
{"learn":[0.1993282391],"iteration":36,"passed_time":7.693226137,"remaining_time":200.2318046},
{"learn":[0.1970057579],"iteration":37,"passed_time":7.871370779,"remaining_time":199.2699655},
{"learn":[0.1954751565],"iteration":38,"passed_time":8.051768785,"remaining_time":198.4038411},
{"learn":[0.1933724678],"iteration":39,"passed_time":8.234441074,"remaining_time":197.6265858},
{"learn":[0.191794931],"iteration":40,"passed_time":8.409572149,"remaining_time":196.7019437},
{"learn":[0.189772925],"iteration":41,"passed_time":8.594273371,"remaining_time":196.0312831},
{"learn":[0.1878302831],"iteration":42,"passed_time":8.80109218,"remaining_time":195.8754702},
{"learn":[0.1862048681],"iteration":43,"passed_time":9.008553201,"remaining_time":195.7312923},
{"learn":[0.1844035112],"iteration":44,"passed_time":9.216264283,"remaining_time":195.5896087},
{"learn":[0.18309496],"iteration":45,"passed_time":9.476113223,"remaining_time":196.5263481},
{"learn":[0.181892439],"iteration":46,"passed_time":9.762689164,"remaining_time":197.9541016},
{"learn":[0.1801802984],"iteration":47,"passed_time":10.01140385,"remaining_time":198.5595096},
{"learn":[0.1785852231],"iteration":48,"passed_time":10.26499459,"remaining_time":199.2246909},
{"learn":[0.1772835805],"iteration":49,"passed_time":10.54003983,"remaining_time":200.2607567},
{"learn":[0.1759462393],"iteration":50,"passed_time":10.78620334,"remaining_time":200.7079798},
{"learn":[0.1746468196],"iteration":51,"passed_time":11.01832366,"remaining_time":200.872516},
{"learn":[0.1733483406],"iteration":52,"passed_time":11.21304107,"remaining_time":200.3537715},
{"learn":[0.171998587],"iteration":53,"passed_time":11.44838826,"remaining_time":200.5588017},
{"learn":[0.1709099458],"iteration":54,"passed_time":11.65940696,"remaining_time":200.3298105},
{"learn":[0.1694340339],"iteration":55,"passed_time":11.86541941,"remaining_time":200.01707},
{"learn":[0.1684549295],"iteration":56,"passed_time":12.06722494,"remaining_time":199.6384757},
{"learn":[0.1674973103],"iteration":57,"passed_time":12.27796378,"remaining_time":199.4110668},
{"learn":[0.1664161535],"iteration":58,"passed_time":12.47119991,"remaining_time":198.9050698},
{"learn":[0.1651588055],"iteration":59,"passed_time":12.69327582,"remaining_time":198.8613212},
{"learn":[0.1639790865],"iteration":60,"passed_time":12.88151487,"remaining_time":198.2908601},
{"learn":[0.1631057758],"iteration":61,"passed_time":13.05074677,"remaining_time":197.4451688},
{"learn":[0.1622055402],"iteration":62,"passed_time":13.22485248,"remaining_time":196.6934409},
{"learn":[0.1610430993],"iteration":63,"passed_time":13.39600396,"remaining_time":195.9165579},
{"learn":[0.1602890822],"iteration":64,"passed_time":13.58041436,"remaining_time":195.3490373},
{"learn":[0.1594115202],"iteration":65,"passed_time":13.76387935,"remaining_time":194.7797472},
{"learn":[0.1585728315],"iteration":66,"passed_time":13.94564399,"remaining_time":194.1982962},
{"learn":[0.1575994473],"iteration":67,"passed_time":14.15187822,"remaining_time":193.963978},
{"learn":[0.1565736826],"iteration":68,"passed_time":14.35249746,"remaining_time":193.6547121},
{"learn":[0.1552529335],"iteration":69,"passed_time":14.54114234,"remaining_time":193.1894625},
{"learn":[0.1543460021],"iteration":70,"passed_time":14.72611751,"remaining_time":192.6839883},
{"learn":[0.1535274817],"iteration":71,"passed_time":14.90566791,"remaining_time":192.1174975},
{"learn":[0.1525058746],"iteration":72,"passed_time":15.0874848,"remaining_time":191.5903892},
{"learn":[0.1516486131],"iteration":73,"passed_time":15.28818052,"remaining_time":191.3088535},
{"learn":[0.1507066837],"iteration":74,"passed_time":15.46896549,"remaining_time":190.7839078},
{"learn":[0.1500444889],"iteration":75,"passed_time":15.63285987,"remaining_time":190.0626647},
{"learn":[0.1493331652],"iteration":76,"passed_time":15.83842826,"remaining_time":189.8554452},
{"learn":[0.148362488],"iteration":77,"passed_time":16.02054476,"remaining_time":189.3710547},
{"learn":[0.1475888747],"iteration":78,"passed_time":16.20138839,"remaining_time":188.8794773},
{"learn":[0.1466494982],"iteration":79,"passed_time":16.37628438,"remaining_time":188.3272704},
{"learn":[0.1458585391],"iteration":80,"passed_time":16.53937358,"remaining_time":187.6504237},
{"learn":[0.1450590867],"iteration":81,"passed_time":16.71335166,"remaining_time":187.10801},
{"learn":[0.1444590037],"iteration":82,"passed_time":16.89277576,"remaining_time":186.634643},
{"learn":[0.1435643068],"iteration":83,"passed_time":17.06984868,"remaining_time":186.1426356},
{"learn":[0.1430401509],"iteration":84,"passed_time":17.24684355,"remaining_time":185.6571982},
{"learn":[0.142475616],"iteration":85,"passed_time":17.41789575,"remaining_time":185.1157758},
{"learn":[0.1417694642],"iteration":86,"passed_time":17.60480245,"remaining_time":184.7492487},
{"learn":[0.140854355],"iteration":87,"passed_time":17.77950516,"remaining_time":184.2603262},
{"learn":[0.1399673462],"iteration":88,"passed_time":17.96287958,"remaining_time":183.8672281},
{"learn":[0.1392266457],"iteration":89,"passed_time":18.12881494,"remaining_time":183.3024622},
{"learn":[0.1385561209],"iteration":90,"passed_time":18.30623405,"remaining_time":182.8611731},
{"learn":[0.1379365903],"iteration":91,"passed_time":18.49719127,"remaining_time":182.5592355},
{"learn":[0.1374260444],"iteration":92,"passed_time":18.66951103,"remaining_time":182.0779194},
{"learn":[0.1368540177],"iteration":93,"passed_time":18.85277857,"remaining_time":181.7086956},
{"learn":[0.1362407996],"iteration":94,"passed_time":19.0394825,"remaining_time":181.3761228},
{"learn":[0.1355563274],"iteration":95,"passed_time":19.24810916,"remaining_time":181.2530279},
{"learn":[0.1348603652],"iteration":96,"passed_time":19.43414011,"remaining_time":180.9178197},
{"learn":[0.1342571167],"iteration":97,"passed_time":19.61963135,"remaining_time":180.5806885},
{"learn":[0.1335887964],"iteration":98,"passed_time":19.79678465,"remaining_time":180.1707371},
{"learn":[0.132971914],"iteration":99,"passed_time":19.9744454,"remaining_time":179.7700086},
{"learn":[0.13237025],"iteration":100,"passed_time":20.13274301,"remaining_time":179.2013462},
{"learn":[0.1317293561],"iteration":101,"passed_time":20.31602758,"remaining_time":178.8607134},
{"learn":[0.1311574248],"iteration":102,"passed_time":20.49701424,"remaining_time":178.503124},
{"learn":[0.1303952648],"iteration":103,"passed_time":20.69093868,"remaining_time":178.2603948},
{"learn":[0.1298753188],"iteration":104,"passed_time":20.90722595,"remaining_time":178.2092117},
{"learn":[0.1292923707],"iteration":105,"passed_time":21.2050442,"remaining_time":178.8425426},
{"learn":[0.1288736903],"iteration":106,"passed_time":21.41640634,"remaining_time":178.7369239},
{"learn":[0.1282020981],"iteration":107,"passed_time":21.62282335,"remaining_time":178.588504},
{"learn":[0.12777767],"iteration":108,"passed_time":21.82027947,"remaining_time":178.3657707},
{"learn":[0.1273616396],"iteration":109,"passed_time":22.00144869,"remaining_time":178.0117212},
{"learn":[0.1269129414],"iteration":110,"passed_time":22.17241098,"remaining_time":177.5790393},
{"learn":[0.1264696451],"iteration":111,"passed_time":22.34918687,"remaining_time":177.1971245},
{"learn":[0.1257686395],"iteration":112,"passed_time":22.53170441,"remaining_time":176.8639099},
{"learn":[0.1253850139],"iteration":113,"passed_time":22.70211183,"remaining_time":176.43922},
{"learn":[0.1247904356],"iteration":114,"passed_time":22.88019073,"remaining_time":176.0779895},
{"learn":[0.1244054712],"iteration":115,"passed_time":23.05704596,"remaining_time":175.7105916},
{"learn":[0.123987429],"iteration":116,"passed_time":23.2438687,"remaining_time":175.4216757},
{"learn":[0.1235609687],"iteration":117,"passed_time":23.42333634,"remaining_time":175.079514},
{"learn":[0.1230343415],"iteration":118,"passed_time":23.59649903,"remaining_time":174.6934088},
{"learn":[0.1224112437],"iteration":119,"passed_time":23.76007889,"remaining_time":174.2405785},
{"learn":[0.1220580697],"iteration":120,"passed_time":23.94215582,"remaining_time":173.9269006},
{"learn":[0.1216494643],"iteration":121,"passed_time":24.10656358,"remaining_time":173.4882199},
{"learn":[0.1212458519],"iteration":122,"passed_time":24.27955814,"remaining_time":173.1152235},
{"learn":[0.1207890456],"iteration":123,"passed_time":24.46470216,"remaining_time":172.831283},
{"learn":[0.1203245356],"iteration":124,"passed_time":24.64671552,"remaining_time":172.5270086},
{"learn":[0.1197103785],"iteration":125,"passed_time":24.82314539,"remaining_time":172.185945},
{"learn":[0.1190296962],"iteration":126,"passed_time":24.99210676,"remaining_time":171.7961355},
{"learn":[0.1185677492],"iteration":127,"passed_time":25.16901739,"remaining_time":171.463931},
{"learn":[0.1176558164],"iteration":128,"passed_time":25.33484214,"remaining_time":171.059283},
{"learn":[0.1171904426],"iteration":129,"passed_time":25.50822637,"remaining_time":170.7088996},
{"learn":[0.1167629755],"iteration":130,"passed_time":25.66860521,"remaining_time":170.274946},
{"learn":[0.1161358916],"iteration":131,"passed_time":25.8371679,"remaining_time":169.8989526},
{"learn":[0.1156717548],"iteration":132,"passed_time":26.00201657,"remaining_time":169.5018674},
{"learn":[0.1153475541],"iteration":133,"passed_time":26.18901454,"remaining_time":169.2513925},
{"learn":[0.1147417224],"iteration":134,"passed_time":26.35701958,"remaining_time":168.8801625},
{"learn":[0.1143541492],"iteration":135,"passed_time":26.52986935,"remaining_time":168.5426994},
{"learn":[0.1138432154],"iteration":136,"passed_time":26.69627889,"remaining_time":168.1670707},
{"learn":[0.1135185682],"iteration":137,"passed_time":26.87927403,"remaining_time":167.898074},
{"learn":[0.1129862895],"iteration":138,"passed_time":27.04875983,"remaining_time":167.5466346},
{"learn":[0.1126688159],"iteration":139,"passed_time":27.21321051,"remaining_time":167.1668646},
{"learn":[0.1122607882],"iteration":140,"passed_time":27.37851889,"remaining_time":166.795374},
{"learn":[0.111956081],"iteration":141,"passed_time":27.55035525,"remaining_time":166.466231},
{"learn":[0.1116069271],"iteration":142,"passed_time":27.72816165,"remaining_time":166.1750667},
{"learn":[0.1111527544],"iteration":143,"passed_time":27.90560364,"remaining_time":165.8833106},
{"learn":[0.1107268398],"iteration":144,"passed_time":28.06705126,"remaining_time":165.4988195},
{"learn":[0.1102884925],"iteration":145,"passed_time":28.24284983,"remaining_time":165.2013271},
{"learn":[0.1099159525],"iteration":146,"passed_time":28.42105159,"remaining_time":164.9194354},
{"learn":[0.1095552463],"iteration":147,"passed_time":28.58724022,"remaining_time":164.5697883},
{"learn":[0.1092858425],"iteration":148,"passed_time":28.75315383,"remaining_time":164.221033},
{"learn":[0.1088713013],"iteration":149,"passed_time":28.92587378,"remaining_time":163.9132848},
{"learn":[0.1085442516],"iteration":150,"passed_time":29.09040634,"remaining_time":163.5612913},
{"learn":[0.1079648082],"iteration":151,"passed_time":29.2868498,"remaining_time":163.3897936},
{"learn":[0.1071242525],"iteration":152,"passed_time":29.44659498,"remaining_time":163.0148101},
{"learn":[0.1068141378],"iteration":153,"passed_time":29.61578992,"remaining_time":162.6945342},
{"learn":[0.1065020359],"iteration":154,"passed_time":29.77417296,"remaining_time":162.3172655},
{"learn":[0.1061026197],"iteration":155,"passed_time":29.95434564,"remaining_time":162.0606905},
{"learn":[0.1057472257],"iteration":156,"passed_time":30.13098604,"remaining_time":161.7861225},
{"learn":[0.1053106776],"iteration":157,"passed_time":30.29804973,"remaining_time":161.4617587},
{"learn":[0.1050418615],"iteration":158,"passed_time":30.48758153,"remaining_time":161.2582142},
{"learn":[0.1045438115],"iteration":159,"passed_time":30.66173917,"remaining_time":160.9741306},
{"learn":[0.1040770467],"iteration":160,"passed_time":30.84279121,"remaining_time":160.7273405},
{"learn":[0.1037423464],"iteration":161,"passed_time":31.01418819,"remaining_time":160.4314179},
{"learn":[0.1033218228],"iteration":162,"passed_time":31.20224664,"remaining_time":160.2225794},
{"learn":[0.1029770549],"iteration":163,"passed_time":31.3877588,"remaining_time":160.0010144},
{"learn":[0.10272051],"iteration":164,"passed_time":31.55986822,"remaining_time":159.7120604},
{"learn":[0.1024028136],"iteration":165,"passed_time":31.77391089,"remaining_time":159.6351909},
{"learn":[0.1020171514],"iteration":166,"passed_time":31.96148572,"remaining_time":159.4246563},
{"learn":[0.1016494173],"iteration":167,"passed_time":32.14604735,"remaining_time":159.1994726},
{"learn":[0.1012564036],"iteration":168,"passed_time":32.33397576,"remaining_time":158.9913246},
{"learn":[0.1009837627],"iteration":169,"passed_time":32.51116044,"remaining_time":158.7309598},
{"learn":[0.1007642764],"iteration":170,"passed_time":32.69902625,"remaining_time":158.5233495},
{"learn":[0.1003788866],"iteration":171,"passed_time":32.8751355,"remaining_time":158.2593732},
{"learn":[0.1000711542],"iteration":172,"passed_time":33.05367907,"remaining_time":158.0080496},
{"learn":[0.09980162841],"iteration":173,"passed_time":33.24795836,"remaining_time":157.8322621},
{"learn":[0.09956146845],"iteration":174,"passed_time":33.42741401,"remaining_time":157.5863803},
{"learn":[0.099022029],"iteration":175,"passed_time":33.61768291,"remaining_time":157.3918791},
{"learn":[0.09849116711],"iteration":176,"passed_time":33.8630295,"remaining_time":157.4535213},
{"learn":[0.09819984711],"iteration":177,"passed_time":34.05212946,"remaining_time":157.2519686},
{"learn":[0.09782849734],"iteration":178,"passed_time":34.21766597,"remaining_time":156.9424791},
{"learn":[0.09736263202],"iteration":179,"passed_time":34.39145419,"remaining_time":156.6721802},
{"learn":[0.09702869104],"iteration":180,"passed_time":34.58357038,"remaining_time":156.4858792},
{"learn":[0.09676373739],"iteration":181,"passed_time":34.7725253,"remaining_time":156.285306},
{"learn":[0.09644004015],"iteration":182,"passed_time":34.95484379,"remaining_time":156.0552316},
{"learn":[0.09610834947],"iteration":183,"passed_time":35.12173524,"remaining_time":155.7572606},
{"learn":[0.09576724768],"iteration":184,"passed_time":35.3101983,"remaining_time":155.5557385},
{"learn":[0.09521905734],"iteration":185,"passed_time":35.51195394,"remaining_time":155.4125296},
{"learn":[0.09492369799],"iteration":186,"passed_time":35.71556996,"remaining_time":155.2767828},
{"learn":[0.0946766945],"iteration":187,"passed_time":35.88407845,"remaining_time":154.9886792},
{"learn":[0.09442615509],"iteration":188,"passed_time":36.05489834,"remaining_time":154.7117595},
{"learn":[0.09370232179],"iteration":189,"passed_time":36.24972203,"remaining_time":154.5382887},
{"learn":[0.09338570008],"iteration":190,"passed_time":36.44922173,"remaining_time":154.3843999},
{"learn":[0.09295763328],"iteration":191,"passed_time":36.63076004,"remaining_time":154.1544485},
{"learn":[0.09264864371],"iteration":192,"passed_time":36.92231221,"remaining_time":154.3850049},
{"learn":[0.09233197066],"iteration":193,"passed_time":37.11634937,"remaining_time":154.2050391},
{"learn":[0.09208312401],"iteration":194,"passed_time":37.30357012,"remaining_time":153.9967895},
{"learn":[0.09177626188],"iteration":195,"passed_time":37.48790191,"remaining_time":153.7769038},
{"learn":[0.09161766859],"iteration":196,"passed_time":37.67293479,"remaining_time":153.5602367},
{"learn":[0.09138839428],"iteration":197,"passed_time":37.86011721,"remaining_time":153.352596},
{"learn":[0.09102330391],"iteration":198,"passed_time":38.04177734,"remaining_time":153.1229329},
{"learn":[0.09082076916],"iteration":199,"passed_time":38.24642633,"remaining_time":152.9857053},
{"learn":[0.09055480223],"iteration":200,"passed_time":38.45686481,"remaining_time":152.8708208},
{"learn":[0.09031505952],"iteration":201,"passed_time":38.65451308,"remaining_time":152.7044626},
{"learn":[0.09010141538],"iteration":202,"passed_time":38.85158214,"remaining_time":152.535522},
{"learn":[0.08983655068],"iteration":203,"passed_time":39.02696231,"remaining_time":152.2816765},
{"learn":[0.08942899704],"iteration":204,"passed_time":39.20343496,"remaining_time":152.0328331},
{"learn":[0.08919476362],"iteration":205,"passed_time":39.37020131,"remaining_time":151.7472808},
{"learn":[0.08884325669],"iteration":206,"passed_time":39.53142717,"remaining_time":151.441651},
{"learn":[0.0885885367],"iteration":207,"passed_time":39.74656906,"remaining_time":151.3427053},
{"learn":[0.08830570624],"iteration":208,"passed_time":40.2852017,"remaining_time":152.4669595},
{"learn":[0.08765983123],"iteration":209,"passed_time":40.60779297,"remaining_time":152.7626497},
{"learn":[0.08741932007],"iteration":210,"passed_time":40.89292354,"remaining_time":152.9124013},
{"learn":[0.0871653997],"iteration":211,"passed_time":41.18716412,"remaining_time":153.0919119},
{"learn":[0.08693451881],"iteration":212,"passed_time":41.44504015,"remaining_time":153.1326132},
{"learn":[0.08667481037],"iteration":213,"passed_time":41.74349627,"remaining_time":153.3195704},
{"learn":[0.08645134247],"iteration":214,"passed_time":41.98700471,"remaining_time":153.3013893},
{"learn":[0.08628491438],"iteration":215,"passed_time":42.1950158,"remaining_time":153.1522796},
{"learn":[0.08609847105],"iteration":216,"passed_time":42.46166726,"remaining_time":153.2142187},
{"learn":[0.08586329772],"iteration":217,"passed_time":42.6823116,"remaining_time":153.1081086},
{"learn":[0.08555468504],"iteration":218,"passed_time":43.1093472,"remaining_time":153.736987},
{"learn":[0.08531598495],"iteration":219,"passed_time":43.69009508,"remaining_time":154.9012462},
{"learn":[0.08518144809],"iteration":220,"passed_time":44.07163854,"remaining_time":155.3475404},
{"learn":[0.08504183476],"iteration":221,"passed_time":44.48298548,"remaining_time":155.890823},
{"learn":[0.08489246644],"iteration":222,"passed_time":44.82912516,"remaining_time":156.1983419},
{"learn":[0.08463021242],"iteration":223,"passed_time":45.14154352,"remaining_time":156.3832043},
{"learn":[0.08435867108],"iteration":224,"passed_time":45.41998384,"remaining_time":156.446611},
{"learn":[0.08414269502],"iteration":225,"passed_time":45.72223736,"remaining_time":156.5885474},
{"learn":[0.08389051236],"iteration":226,"passed_time":45.98814502,"remaining_time":156.6028022},
{"learn":[0.08379431046],"iteration":227,"passed_time":46.27844953,"remaining_time":156.6972063},
{"learn":[0.08337286894],"iteration":228,"passed_time":46.53980925,"remaining_time":156.6907988},
{"learn":[0.08316559792],"iteration":229,"passed_time":46.76080744,"remaining_time":156.547051},
{"learn":[0.08258076631],"iteration":230,"passed_time":46.98146139,"remaining_time":156.4014883},
{"learn":[0.08234032576],"iteration":231,"passed_time":47.22534439,"remaining_time":156.3321745},
{"learn":[0.08210814458],"iteration":232,"passed_time":47.54657078,"remaining_time":156.5159648},
{"learn":[0.08199697825],"iteration":233,"passed_time":47.79235148,"remaining_time":156.4484668},
{"learn":[0.08186774529],"iteration":234,"passed_time":48.04729805,"remaining_time":156.4092894},
{"learn":[0.08146074735],"iteration":235,"passed_time":48.36218236,"remaining_time":156.5623192},
{"learn":[0.08128322638],"iteration":236,"passed_time":48.58884875,"remaining_time":156.4273907},
{"learn":[0.08103984686],"iteration":237,"passed_time":48.79512956,"remaining_time":156.2264232},
{"learn":[0.08092484658],"iteration":238,"passed_time":48.97553399,"remaining_time":155.9430183},
{"learn":[0.08066477317],"iteration":239,"passed_time":49.20959019,"remaining_time":155.8303689},
{"learn":[0.08045269251],"iteration":240,"passed_time":49.41367299,"remaining_time":155.6223145},
{"learn":[0.08016994091],"iteration":241,"passed_time":49.61120178,"remaining_time":155.3937642},
{"learn":[0.08004075105],"iteration":242,"passed_time":49.80255133,"remaining_time":155.1462196},
{"learn":[0.07969741913],"iteration":243,"passed_time":50.00411558,"remaining_time":154.9307843},
{"learn":[0.0795108731],"iteration":244,"passed_time":50.19611022,"remaining_time":154.6859723},
{"learn":[0.07922847821],"iteration":245,"passed_time":50.41154024,"remaining_time":154.5134201},
{"learn":[0.0791421661],"iteration":246,"passed_time":50.62132271,"remaining_time":154.3233037},
{"learn":[0.07904364604],"iteration":247,"passed_time":50.847646,"remaining_time":154.1831846},
{"learn":[0.07890828481],"iteration":248,"passed_time":51.04558828,"remaining_time":153.9567743},
{"learn":[0.07853343487],"iteration":249,"passed_time":51.24473292,"remaining_time":153.7341988},
{"learn":[0.07839825979],"iteration":250,"passed_time":51.42528899,"remaining_time":153.4563405},
{"learn":[0.078182579],"iteration":251,"passed_time":51.66720926,"remaining_time":153.3613989},
{"learn":[0.07803751139],"iteration":252,"passed_time":51.84797082,"remaining_time":153.0847202},
{"learn":[0.07794284362],"iteration":253,"passed_time":52.02047196,"remaining_time":152.7845358},
{"learn":[0.07778377533],"iteration":254,"passed_time":52.19098827,"remaining_time":152.479554},
{"learn":[0.07765909984],"iteration":255,"passed_time":52.34003895,"remaining_time":152.1132382},
{"learn":[0.07750323277],"iteration":256,"passed_time":52.5163567,"remaining_time":151.8274437},
{"learn":[0.07741068327],"iteration":257,"passed_time":52.68871439,"remaining_time":151.5311088},
{"learn":[0.07723531173],"iteration":258,"passed_time":52.85611361,"remaining_time":151.2215451},
{"learn":[0.07694535439],"iteration":259,"passed_time":53.02364988,"remaining_time":150.913465},
{"learn":[0.07686058925],"iteration":260,"passed_time":53.19030441,"remaining_time":150.6039653},
{"learn":[0.07632811803],"iteration":261,"passed_time":53.3679632,"remaining_time":150.3265528},
{"learn":[0.07626119394],"iteration":262,"passed_time":53.56567631,"remaining_time":150.1060967},
{"learn":[0.07613646342],"iteration":263,"passed_time":53.76412463,"remaining_time":149.8878626},
{"learn":[0.07597722549],"iteration":264,"passed_time":53.93937593,"remaining_time":149.6054389},
{"learn":[0.07586439665],"iteration":265,"passed_time":54.12440122,"remaining_time":149.3507913},
{"learn":[0.07566771232],"iteration":266,"passed_time":54.28544666,"remaining_time":149.030833},
{"learn":[0.07559937789],"iteration":267,"passed_time":54.43739238,"remaining_time":148.6872061},
{"learn":[0.07534607924],"iteration":268,"passed_time":54.59901499,"remaining_time":148.371301},
{"learn":[0.07526678122],"iteration":269,"passed_time":54.76735899,"remaining_time":148.0747113},
{"learn":[0.07519118419],"iteration":270,"passed_time":54.94076173,"remaining_time":147.7926764},
{"learn":[0.07478858049],"iteration":271,"passed_time":55.12247125,"remaining_time":147.5336731},
{"learn":[0.07448765865],"iteration":272,"passed_time":55.30543071,"remaining_time":147.2785646},
{"learn":[0.07421180835],"iteration":273,"passed_time":55.49965323,"remaining_time":147.0538257},
{"learn":[0.07408967568],"iteration":274,"passed_time":55.67841119,"remaining_time":146.7885386},
{"learn":[0.07386535223],"iteration":275,"passed_time":55.84644844,"remaining_time":146.495756},
{"learn":[0.07366214349],"iteration":276,"passed_time":56.01425684,"remaining_time":146.2032769},
{"learn":[0.07346834586],"iteration":277,"passed_time":56.18277633,"remaining_time":145.9135414},
{"learn":[0.0733812919],"iteration":278,"passed_time":56.34232516,"remaining_time":145.6014926},
{"learn":[0.07304341518],"iteration":279,"passed_time":56.50038109,"remaining_time":145.2866942},
{"learn":[0.07294327846],"iteration":280,"passed_time":56.66821335,"remaining_time":144.9980263},
{"learn":[0.0728818059],"iteration":281,"passed_time":56.82940838,"remaining_time":144.6933164},
{"learn":[0.07281766396],"iteration":282,"passed_time":56.99328014,"remaining_time":144.3964023},
{"learn":[0.07254674985],"iteration":283,"passed_time":57.14376322,"remaining_time":144.0666706},
{"learn":[0.07239402991],"iteration":284,"passed_time":57.31466997,"remaining_time":143.7894352},
{"learn":[0.07220693735],"iteration":285,"passed_time":57.48338083,"remaining_time":143.5074612},
{"learn":[0.07209527401],"iteration":286,"passed_time":57.64080604,"remaining_time":143.1982394},
{"learn":[0.07170923398],"iteration":287,"passed_time":57.82778617,"remaining_time":142.963138},
{"learn":[0.07163194235],"iteration":288,"passed_time":58.0273961,"remaining_time":142.7594416},
{"learn":[0.071519108],"iteration":289,"passed_time":58.20823739,"remaining_time":142.5098226},
{"learn":[0.07145131368],"iteration":290,"passed_time":58.38333735,"remaining_time":142.2466879},
{"learn":[0.0713917127],"iteration":291,"passed_time":58.55485923,"remaining_time":141.9754806},
{"learn":[0.07132731126],"iteration":292,"passed_time":58.71971012,"remaining_time":141.6888568},
{"learn":[0.07086226207],"iteration":293,"passed_time":58.89352911,"remaining_time":141.4245971},
{"learn":[0.07067499803],"iteration":294,"passed_time":59.05445652,"remaining_time":141.1301419},
{"learn":[0.07020778473],"iteration":295,"passed_time":59.21985763,"remaining_time":140.847229},
{"learn":[0.06988867017],"iteration":296,"passed_time":59.36840736,"remaining_time":140.5252201},
{"learn":[0.06962419106],"iteration":297,"passed_time":59.5336421,"remaining_time":140.2436804},
{"learn":[0.0695269603],"iteration":298,"passed_time":59.69676223,"remaining_time":139.9579609},
{"learn":[0.06928593379],"iteration":299,"passed_time":59.87322145,"remaining_time":139.7041834},
{"learn":[0.06922369187],"iteration":300,"passed_time":60.04050244,"remaining_time":139.4296053},
{"learn":[0.06904849135],"iteration":301,"passed_time":60.20832034,"remaining_time":139.1569788},
{"learn":[0.06883457578],"iteration":302,"passed_time":60.3836967,"remaining_time":138.902431},
{"learn":[0.0686098924],"iteration":303,"passed_time":60.55160672,"remaining_time":138.6313101},
{"learn":[0.06855304287],"iteration":304,"passed_time":60.70963019,"remaining_time":138.3383376},
{"learn":[0.06842857187],"iteration":305,"passed_time":60.8518115,"remaining_time":138.0103176},
{"learn":[0.06836587787],"iteration":306,"passed_time":61.00882916,"remaining_time":137.7169987},
{"learn":[0.06815462525],"iteration":307,"passed_time":61.17337028,"remaining_time":137.4414683},
{"learn":[0.06802556331],"iteration":308,"passed_time":61.34394036,"remaining_time":137.1801385},
{"learn":[0.06772772257],"iteration":309,"passed_time":61.51804629,"remaining_time":136.9272643},
{"learn":[0.06741372851],"iteration":310,"passed_time":61.6896744,"remaining_time":136.6694073},
{"learn":[0.06723991862],"iteration":311,"passed_time":61.84348401,"remaining_time":136.3728109},
{"learn":[0.06696892427],"iteration":312,"passed_time":62.012415,"remaining_time":136.1103166},
{"learn":[0.06675985776],"iteration":313,"passed_time":62.18907666,"remaining_time":135.8653076},
{"learn":[0.06667366945],"iteration":314,"passed_time":62.3659918,"remaining_time":135.6212838},
{"learn":[0.06646586427],"iteration":315,"passed_time":62.51334788,"remaining_time":135.3137024},
{"learn":[0.06624747698],"iteration":316,"passed_time":62.67553857,"remaining_time":135.0390941},
{"learn":[0.06611391764],"iteration":317,"passed_time":62.83087786,"remaining_time":134.7504991},
{"learn":[0.06589669539],"iteration":318,"passed_time":62.990657,"remaining_time":134.4722176},
{"learn":[0.06576205309],"iteration":319,"passed_time":63.15520451,"remaining_time":134.2048096},
{"learn":[0.06556689556],"iteration":320,"passed_time":63.32010803,"remaining_time":133.9387955},
{"learn":[0.06536272122],"iteration":321,"passed_time":63.52075845,"remaining_time":133.7486777},
{"learn":[0.06522293641],"iteration":322,"passed_time":63.68352127,"remaining_time":133.4790833},
{"learn":[0.06516994055],"iteration":323,"passed_time":63.86447365,"remaining_time":133.2480993},
{"learn":[0.06511724729],"iteration":324,"passed_time":64.03584593,"remaining_time":132.9975262},
{"learn":[0.06498147158],"iteration":325,"passed_time":64.20705882,"remaining_time":132.7471093},
{"learn":[0.06490905881],"iteration":326,"passed_time":64.37054158,"remaining_time":132.4812675},
{"learn":[0.06485118499],"iteration":327,"passed_time":64.53316437,"remaining_time":132.214288},
{"learn":[0.06468709661],"iteration":328,"passed_time":64.69336136,"remaining_time":131.9429953},
{"learn":[0.06445987454],"iteration":329,"passed_time":64.85486492,"remaining_time":131.6750288},
{"learn":[0.06427757419],"iteration":330,"passed_time":65.00522626,"remaining_time":131.3851854},
{"learn":[0.0641591824],"iteration":331,"passed_time":65.14106361,"remaining_time":131.0669593},
{"learn":[0.064103751],"iteration":332,"passed_time":65.29246224,"remaining_time":130.7809979},
{"learn":[0.0640471518],"iteration":333,"passed_time":65.45211675,"remaining_time":130.5123047},
{"learn":[0.06399559975],"iteration":334,"passed_time":65.60801146,"remaining_time":130.2367989},
{"learn":[0.06387679852],"iteration":335,"passed_time":65.77877141,"remaining_time":129.9913816},
{"learn":[0.06343760399],"iteration":336,"passed_time":65.92362837,"remaining_time":129.6954469},
{"learn":[0.06324028831],"iteration":337,"passed_time":66.06699543,"remaining_time":129.3974881},
{"learn":[0.063012533],"iteration":338,"passed_time":66.23801128,"remaining_time":129.1543524},
{"learn":[0.06295532905],"iteration":339,"passed_time":66.39630281,"remaining_time":128.8869408},
{"learn":[0.06276818972],"iteration":340,"passed_time":66.55615133,"remaining_time":128.6231781},
{"learn":[0.06264375357],"iteration":341,"passed_time":66.70824869,"remaining_time":128.3451101},
{"learn":[0.06251191313],"iteration":342,"passed_time":66.85822641,"remaining_time":128.0637165},
{"learn":[0.06231657863],"iteration":343,"passed_time":67.00140615,"remaining_time":127.7701233},
{"learn":[0.06218808844],"iteration":344,"passed_time":67.15148396,"remaining_time":127.4904985},
{"learn":[0.06195724377],"iteration":345,"passed_time":67.31750287,"remaining_time":127.241754},
{"learn":[0.06191156048],"iteration":346,"passed_time":67.45830612,"remaining_time":126.9460343},
{"learn":[0.06183686119],"iteration":347,"passed_time":67.63202779,"remaining_time":126.7128797},
{"learn":[0.06170199834],"iteration":348,"passed_time":67.79389425,"remaining_time":126.4579517},
{"learn":[0.06149457739],"iteration":349,"passed_time":67.96714812,"remaining_time":126.2247036},
{"learn":[0.06137554966],"iteration":350,"passed_time":68.1192253,"remaining_time":125.9526416},
{"learn":[0.06101414607],"iteration":351,"passed_time":68.27054933,"remaining_time":125.6798749},
{"learn":[0.06089111016],"iteration":352,"passed_time":68.42504542,"remaining_time":125.4136102},
{"learn":[0.06084189919],"iteration":353,"passed_time":68.57785263,"remaining_time":125.1448949},
{"learn":[0.06078900695],"iteration":354,"passed_time":68.7321107,"remaining_time":124.8794687},
{"learn":[0.06071455708],"iteration":355,"passed_time":68.89059573,"remaining_time":124.6223136},
{"learn":[0.06052539578],"iteration":356,"passed_time":69.05333767,"remaining_time":124.3733785},
{"learn":[0.06044992575],"iteration":357,"passed_time":69.20467307,"remaining_time":124.1044696},
{"learn":[0.06031529858],"iteration":358,"passed_time":69.35496845,"remaining_time":123.8343587},
{"learn":[0.06026112987],"iteration":359,"passed_time":69.5044992,"remaining_time":123.5635541},
{"learn":[0.05990863121],"iteration":360,"passed_time":69.66162029,"remaining_time":123.306857},
{"learn":[0.05970314879],"iteration":361,"passed_time":69.82199721,"remaining_time":123.0564481},
{"learn":[0.0593469982],"iteration":362,"passed_time":69.97770281,"remaining_time":122.798338},
{"learn":[0.05908548832],"iteration":363,"passed_time":70.13798707,"remaining_time":122.5487906},
{"learn":[0.05895553736],"iteration":364,"passed_time":70.2969899,"remaining_time":122.297503},
{"learn":[0.05880907866],"iteration":365,"passed_time":70.44575782,"remaining_time":122.0289903},
{"learn":[0.05868072739],"iteration":366,"passed_time":70.60807419,"remaining_time":121.7844985},
{"learn":[0.05849625698],"iteration":367,"passed_time":70.77165181,"remaining_time":121.5426194},
{"learn":[0.05837966937],"iteration":368,"passed_time":70.91509512,"remaining_time":121.2667345},
{"learn":[0.05816254432],"iteration":369,"passed_time":71.06379346,"remaining_time":121.0005132},
{"learn":[0.05797593181],"iteration":370,"passed_time":71.22424506,"remaining_time":120.7548521},
{"learn":[0.05775263539],"iteration":371,"passed_time":71.38633481,"remaining_time":120.5124147},
{"learn":[0.05770632074],"iteration":372,"passed_time":71.52443046,"remaining_time":120.2300748},
{"learn":[0.05763864563],"iteration":373,"passed_time":71.68992701,"remaining_time":119.9943698},
{"learn":[0.05759124206],"iteration":374,"passed_time":71.84625431,"remaining_time":119.7437572},
{"learn":[0.05743285418],"iteration":375,"passed_time":72.00373158,"remaining_time":119.4955545},
{"learn":[0.05730209305],"iteration":376,"passed_time":72.19436471,"remaining_time":119.3026239},
{"learn":[0.05721326929],"iteration":377,"passed_time":72.36666618,"remaining_time":119.0795406},
{"learn":[0.05704784256],"iteration":378,"passed_time":72.52243895,"remaining_time":118.8296427},
{"learn":[0.05673251473],"iteration":379,"passed_time":72.72440634,"remaining_time":118.6556103},
{"learn":[0.05649446478],"iteration":380,"passed_time":72.90729305,"remaining_time":118.4504315},
{"learn":[0.05637184794],"iteration":381,"passed_time":73.07898991,"remaining_time":118.2272664},
{"learn":[0.05627005971],"iteration":382,"passed_time":73.25245983,"remaining_time":118.0072264},
{"learn":[0.05612032047],"iteration":383,"passed_time":73.41521679,"remaining_time":117.7702436},
{"learn":[0.05606927184],"iteration":384,"passed_time":73.57676781,"remaining_time":117.53172},
{"learn":[0.05602845458],"iteration":385,"passed_time":73.73909523,"remaining_time":117.2948302},
{"learn":[0.05595657413],"iteration":386,"passed_time":73.88736827,"remaining_time":117.036064},
{"learn":[0.05591629973],"iteration":387,"passed_time":74.04862158,"remaining_time":116.7983413},
{"learn":[0.05569192263],"iteration":388,"passed_time":74.20583936,"remaining_time":116.5546731},
{"learn":[0.05559663314],"iteration":389,"passed_time":74.36342638,"remaining_time":116.3120259},
{"learn":[0.05555840868],"iteration":390,"passed_time":74.52537317,"remaining_time":116.0766043},
{"learn":[0.05551486703],"iteration":391,"passed_time":74.68474579,"remaining_time":115.8375649},
{"learn":[0.05537825639],"iteration":392,"passed_time":74.83336701,"remaining_time":115.5823251},
{"learn":[0.05534047301],"iteration":393,"passed_time":74.97686834,"remaining_time":115.3197518},
{"learn":[0.05525922913],"iteration":394,"passed_time":75.11868537,"remaining_time":115.0552016},
{"learn":[0.05522112938],"iteration":395,"passed_time":75.27404967,"remaining_time":114.8119344},
{"learn":[0.05515204806],"iteration":396,"passed_time":75.4280651,"remaining_time":114.5670611},
{"learn":[0.05511519634],"iteration":397,"passed_time":75.57338734,"remaining_time":114.3094954},
{"learn":[0.05502193249],"iteration":398,"passed_time":75.71954283,"remaining_time":114.0537475},
{"learn":[0.05498537054],"iteration":399,"passed_time":75.87902577,"remaining_time":113.8185387},
{"learn":[0.05494873065],"iteration":400,"passed_time":76.0360258,"remaining_time":113.5799986},
{"learn":[0.05491288992],"iteration":401,"passed_time":76.20540654,"remaining_time":113.3602814},
{"learn":[0.05487744992],"iteration":402,"passed_time":76.36817158,"remaining_time":113.1310135},
{"learn":[0.05484258578],"iteration":403,"passed_time":76.52626841,"remaining_time":112.8951881},
{"learn":[0.05465106093],"iteration":404,"passed_time":76.67713424,"remaining_time":112.6491231},
{"learn":[0.05451653095],"iteration":405,"passed_time":76.83644339,"remaining_time":112.4158802},
{"learn":[0.05444508608],"iteration":406,"passed_time":76.98448653,"remaining_time":112.166586},
{"learn":[0.05441051767],"iteration":407,"passed_time":77.13722702,"remaining_time":111.9246039},
{"learn":[0.05418509703],"iteration":408,"passed_time":77.30467569,"remaining_time":111.7043113},
{"learn":[0.05415099401],"iteration":409,"passed_time":77.46978292,"remaining_time":111.4809071},
{"learn":[0.05411649942],"iteration":410,"passed_time":77.61550679,"remaining_time":111.2300085},
{"learn":[0.05408309927],"iteration":411,"passed_time":77.76884484,"remaining_time":110.9904873},
{"learn":[0.05405006775],"iteration":412,"passed_time":77.9245392,"remaining_time":110.7547325},
{"learn":[0.05401679002],"iteration":413,"passed_time":78.08024747,"remaining_time":110.5193841},
{"learn":[0.05383696143],"iteration":414,"passed_time":78.24858792,"remaining_time":110.3022263},
{"learn":[0.05380285107],"iteration":415,"passed_time":78.41329267,"remaining_time":110.0801993},
{"learn":[0.0537712574],"iteration":416,"passed_time":78.57572538,"remaining_time":109.8552707},
{"learn":[0.05367137927],"iteration":417,"passed_time":78.73000646,"remaining_time":109.6192913},
{"learn":[0.05363959395],"iteration":418,"passed_time":78.88067732,"remaining_time":109.3786958},
{"learn":[0.05360841201],"iteration":419,"passed_time":79.04211711,"remaining_time":109.1533998},
{"learn":[0.05357711774],"iteration":420,"passed_time":79.20441623,"remaining_time":108.9295891},
{"learn":[0.05337471366],"iteration":421,"passed_time":79.36869716,"remaining_time":108.7087843},
{"learn":[0.05333914252],"iteration":422,"passed_time":79.52567168,"remaining_time":108.4782803},
{"learn":[0.05316766409],"iteration":423,"passed_time":79.68134533,"remaining_time":108.2463559},
{"learn":[0.05313579027],"iteration":424,"passed_time":79.82528548,"remaining_time":107.9989157},
{"learn":[0.05300816114],"iteration":425,"passed_time":79.99242621,"remaining_time":107.7832222},
{"learn":[0.05270190697],"iteration":426,"passed_time":80.16412443,"remaining_time":107.5738719},
{"learn":[0.05265205778],"iteration":427,"passed_time":80.3469814,"remaining_time":107.3796107},
{"learn":[0.05262093636],"iteration":428,"passed_time":80.53943051,"remaining_time":107.1981698},
{"learn":[0.05259014093],"iteration":429,"passed_time":80.79994828,"remaining_time":107.1069082},
{"learn":[0.05255435063],"iteration":430,"passed_time":80.98609621,"remaining_time":106.9166792},
{"learn":[0.05244903244],"iteration":431,"passed_time":81.16078008,"remaining_time":106.711396},
{"learn":[0.05241777851],"iteration":432,"passed_time":81.33871387,"remaining_time":106.5105098},
{"learn":[0.05238648103],"iteration":433,"passed_time":81.53156177,"remaining_time":106.3291796},
{"learn":[0.05235603864],"iteration":434,"passed_time":81.70194063,"remaining_time":106.1186125},
{"learn":[0.05217396434],"iteration":435,"passed_time":81.87514553,"remaining_time":105.9118855},
{"learn":[0.05214315607],"iteration":436,"passed_time":82.03688736,"remaining_time":105.6905437},
{"learn":[0.05211236614],"iteration":437,"passed_time":82.2124529,"remaining_time":105.4872113},
{"learn":[0.05197650378],"iteration":438,"passed_time":82.37179803,"remaining_time":105.2632772},
{"learn":[0.05194512789],"iteration":439,"passed_time":82.5312006,"remaining_time":105.0397099},
{"learn":[0.05191515822],"iteration":440,"passed_time":82.69169994,"remaining_time":104.8178237},
{"learn":[0.05188532013],"iteration":441,"passed_time":82.85511683,"remaining_time":104.5998986},
{"learn":[0.05185519365],"iteration":442,"passed_time":83.00538416,"remaining_time":104.3656862},
{"learn":[0.05182546973],"iteration":443,"passed_time":83.18331972,"remaining_time":104.1664995},
{"learn":[0.05157650572],"iteration":444,"passed_time":83.34847292,"remaining_time":103.9514662},
{"learn":[0.05145704288],"iteration":445,"passed_time":83.50076216,"remaining_time":103.7206777},
{"learn":[0.05135920185],"iteration":446,"passed_time":83.65951432,"remaining_time":103.4982358},
{"learn":[0.05133008819],"iteration":447,"passed_time":83.81301716,"remaining_time":103.2696104},
{"learn":[0.05130080076],"iteration":448,"passed_time":83.966633,"remaining_time":103.0414583},
{"learn":[0.05127183428],"iteration":449,"passed_time":84.11601611,"remaining_time":102.8084641},
{"learn":[0.05124308925],"iteration":450,"passed_time":84.27046095,"remaining_time":102.5820024},
{"learn":[0.05121356249],"iteration":451,"passed_time":84.43531531,"remaining_time":102.3684796},
{"learn":[0.0511850999],"iteration":452,"passed_time":84.57425601,"remaining_time":102.1238809},
{"learn":[0.05115696421],"iteration":453,"passed_time":84.71120087,"remaining_time":101.8773473},
{"learn":[0.05112843697],"iteration":454,"passed_time":84.8626947,"remaining_time":101.6487222},
{"learn":[0.0511008877],"iteration":455,"passed_time":85.03537535,"remaining_time":101.4457109},
{"learn":[0.05107182494],"iteration":456,"passed_time":85.19213597,"remaining_time":101.2239165},
{"learn":[0.05096620046],"iteration":457,"passed_time":85.34491633,"remaining_time":100.9976957},
{"learn":[0.05090948664],"iteration":458,"passed_time":85.50765152,"remaining_time":100.7835283},
{"learn":[0.05088166182],"iteration":459,"passed_time":85.66631211,"remaining_time":100.5648012},
{"learn":[0.05084661612],"iteration":460,"passed_time":85.82566927,"remaining_time":100.3471491},
{"learn":[0.05081903338],"iteration":461,"passed_time":85.9800523,"remaining_time":100.123957},
{"learn":[0.05079229887],"iteration":462,"passed_time":86.11886783,"remaining_time":99.88300654},
{"learn":[0.05071533276],"iteration":463,"passed_time":86.28899369,"remaining_time":99.67866513},
{"learn":[0.05068834699],"iteration":464,"passed_time":86.44161061,"remaining_time":99.45432618},
{"learn":[0.05066194213],"iteration":465,"passed_time":86.60193334,"remaining_time":99.23912533},
{"learn":[0.05063472711],"iteration":466,"passed_time":86.74287534,"remaining_time":99.00203973},
{"learn":[0.05060883256],"iteration":467,"passed_time":86.89936057,"remaining_time":98.78303381},
{"learn":[0.05058230162],"iteration":468,"passed_time":87.0492363,"remaining_time":98.55681125},
{"learn":[0.05053330568],"iteration":469,"passed_time":87.2023,"remaining_time":98.33450851},
{"learn":[0.05032753532],"iteration":470,"passed_time":87.35501348,"remaining_time":98.11210644},
{"learn":[0.05027893277],"iteration":471,"passed_time":87.50894913,"remaining_time":97.89136682},
{"learn":[0.05025206804],"iteration":472,"passed_time":87.65961681,"remaining_time":97.66726862},
{"learn":[0.05022630233],"iteration":473,"passed_time":87.83176919,"remaining_time":97.46732193},
{"learn":[0.05020076632],"iteration":474,"passed_time":87.98549458,"remaining_time":97.24712559},
{"learn":[0.05001587776],"iteration":475,"passed_time":88.20881759,"remaining_time":97.10382441},
{"learn":[0.04998981402],"iteration":476,"passed_time":88.38492874,"remaining_time":96.90842292},
{"learn":[0.04996472276],"iteration":477,"passed_time":88.55618537,"remaining_time":96.70780076},
{"learn":[0.04992721081],"iteration":478,"passed_time":88.70514413,"remaining_time":96.48304821},
{"learn":[0.04990216952],"iteration":479,"passed_time":88.86490482,"remaining_time":96.27031356},
{"learn":[0.04987708101],"iteration":480,"passed_time":89.02317073,"remaining_time":96.0561863},
{"learn":[0.04985235609],"iteration":481,"passed_time":89.16761692,"remaining_time":95.82743893},
{"learn":[0.04982744226],"iteration":482,"passed_time":89.32085165,"remaining_time":95.60844783},
{"learn":[0.04967824312],"iteration":483,"passed_time":89.48853147,"remaining_time":95.40512859},
{"learn":[0.04956799104],"iteration":484,"passed_time":89.64306978,"remaining_time":95.18800193},
{"learn":[0.0495434518],"iteration":485,"passed_time":89.79656997,"remaining_time":94.97003491},
{"learn":[0.04931549201],"iteration":486,"passed_time":89.94783263,"remaining_time":94.74997565},
{"learn":[0.04929104814],"iteration":487,"passed_time":90.09557101,"remaining_time":94.52650073},
{"learn":[0.04919536251],"iteration":488,"passed_time":90.23913143,"remaining_time":94.29896965},
{"learn":[0.04917113552],"iteration":489,"passed_time":90.4024528,"remaining_time":94.09234883},
{"learn":[0.04913234252],"iteration":490,"passed_time":90.56019244,"remaining_time":93.88011803},
{"learn":[0.04909732021],"iteration":491,"passed_time":90.73641736,"remaining_time":93.68719516},
{"learn":[0.04894846128],"iteration":492,"passed_time":90.89904646,"remaining_time":93.48035813},
{"learn":[0.04886043439],"iteration":493,"passed_time":91.07010486,"remaining_time":93.28233413},
{"learn":[0.04883573468],"iteration":494,"passed_time":91.22928982,"remaining_time":93.07230578},
{"learn":[0.0488123582],"iteration":495,"passed_time":91.39689914,"remaining_time":92.87104267},
{"learn":[0.04869816441],"iteration":496,"passed_time":91.53391106,"remaining_time":92.63894821},
{"learn":[0.0486567699],"iteration":497,"passed_time":91.70945286,"remaining_time":92.44607497},
{"learn":[0.04848212325],"iteration":498,"passed_time":91.88432992,"remaining_time":92.25260379},
{"learn":[0.04845880591],"iteration":499,"passed_time":92.0688839,"remaining_time":92.0688839},
{"learn":[0.04836340822],"iteration":500,"passed_time":92.23656531,"remaining_time":91.86835547},
{"learn":[0.04821801002],"iteration":501,"passed_time":92.40032009,"remaining_time":91.66406255},
{"learn":[0.04806937025],"iteration":502,"passed_time":92.56797373,"remaining_time":91.46378319},
{"learn":[0.04804563293],"iteration":503,"passed_time":92.73413867,"remaining_time":91.26216822},
{"learn":[0.04778495752],"iteration":504,"passed_time":92.88911998,"remaining_time":91.04973147},
{"learn":[0.04776114409],"iteration":505,"passed_time":93.04425225,"remaining_time":90.83766919},
{"learn":[0.04773766811],"iteration":506,"passed_time":93.20214518,"remaining_time":90.62851592},
{"learn":[0.04764303565],"iteration":507,"passed_time":93.36439001,"remaining_time":90.4237793},
{"learn":[0.04761297749],"iteration":508,"passed_time":93.50719314,"remaining_time":90.20045546},
{"learn":[0.04758920211],"iteration":509,"passed_time":93.66752503,"remaining_time":89.99428876},
{"learn":[0.04756626624],"iteration":510,"passed_time":93.81448778,"remaining_time":89.77550787},
{"learn":[0.04754288655],"iteration":511,"passed_time":93.97482834,"remaining_time":89.56975826},
{"learn":[0.04752025329],"iteration":512,"passed_time":94.15224739,"remaining_time":89.3803986},
{"learn":[0.04749732384],"iteration":513,"passed_time":94.32033776,"remaining_time":89.18226489},
{"learn":[0.04747483776],"iteration":514,"passed_time":94.49053311,"remaining_time":88.98623021},
{"learn":[0.04745247639],"iteration":515,"passed_time":94.65340868,"remaining_time":88.78342985},
{"learn":[0.04743018334],"iteration":516,"passed_time":94.81213345,"remaining_time":88.5769061},
{"learn":[0.04740814796],"iteration":517,"passed_time":95.03133626,"remaining_time":88.42684184},
{"learn":[0.04723899594],"iteration":518,"passed_time":95.1959899,"remaining_time":88.22595596},
{"learn":[0.04721691746],"iteration":519,"passed_time":95.36079926,"remaining_time":88.02535316},
{"learn":[0.04710280483],"iteration":520,"passed_time":95.52698641,"remaining_time":87.82615449},
{"learn":[0.0470806727],"iteration":521,"passed_time":95.70444189,"remaining_time":87.63740081},
{"learn":[0.04690696184],"iteration":522,"passed_time":95.86411719,"remaining_time":87.432474},
{"learn":[0.0468647049],"iteration":523,"passed_time":96.02223631,"remaining_time":87.22630626},
{"learn":[0.04684322064],"iteration":524,"passed_time":96.15414322,"remaining_time":86.99660577},
{"learn":[0.04676911372],"iteration":525,"passed_time":96.31391,"remaining_time":86.79238277},
{"learn":[0.04668348202],"iteration":526,"passed_time":96.48182788,"remaining_time":86.59564438},
{"learn":[0.04652159214],"iteration":527,"passed_time":96.63464181,"remaining_time":86.38551313},
{"learn":[0.04650011888],"iteration":528,"passed_time":96.78865897,"remaining_time":86.1766699},
{"learn":[0.0462752301],"iteration":529,"passed_time":96.95597148,"remaining_time":85.97982377},
{"learn":[0.04617839364],"iteration":530,"passed_time":97.11937427,"remaining_time":85.77963565},
{"learn":[0.04615695431],"iteration":531,"passed_time":97.28729229,"remaining_time":85.58355788},
{"learn":[0.04613575431],"iteration":532,"passed_time":97.44141725,"remaining_time":85.37550067},
{"learn":[0.04601532863],"iteration":533,"passed_time":97.60321931,"remaining_time":85.17434494},
{"learn":[0.04599371598],"iteration":534,"passed_time":97.7711509,"remaining_time":84.97866387},
{"learn":[0.04597312395],"iteration":535,"passed_time":97.92570053,"remaining_time":84.77150195},
{"learn":[0.04595200419],"iteration":536,"passed_time":98.07207798,"remaining_time":84.55748995},
{"learn":[0.04593128012],"iteration":537,"passed_time":98.22576134,"remaining_time":84.35000323},
{"learn":[0.04584886615],"iteration":538,"passed_time":98.38158596,"remaining_time":84.14454755},
{"learn":[0.04582754924],"iteration":539,"passed_time":98.53866799,"remaining_time":83.9403468},
{"learn":[0.04580763808],"iteration":540,"passed_time":98.68811345,"remaining_time":83.72984117},
{"learn":[0.0457861396],"iteration":541,"passed_time":98.84124034,"remaining_time":83.52267173},
{"learn":[0.04561895086],"iteration":542,"passed_time":98.99272012,"remaining_time":83.31431509},
{"learn":[0.04559765779],"iteration":543,"passed_time":99.150899,"remaining_time":83.11178298},
{"learn":[0.04557703321],"iteration":544,"passed_time":99.30361702,"remaining_time":82.90485457},
{"learn":[0.04555796797],"iteration":545,"passed_time":99.45136482,"remaining_time":82.693992},
{"learn":[0.04542500102],"iteration":546,"passed_time":99.59882214,"remaining_time":82.48311961},
{"learn":[0.04540446859],"iteration":547,"passed_time":99.74322622,"remaining_time":82.26996031},
{"learn":[0.04536600159],"iteration":548,"passed_time":99.90218589,"remaining_time":82.06900881},
{"learn":[0.04525164137],"iteration":549,"passed_time":100.0603312,"remaining_time":81.86754368},
{"learn":[0.0451182966],"iteration":550,"passed_time":100.2128374,"remaining_time":81.66164065},
{"learn":[0.04509814611],"iteration":551,"passed_time":100.3695426,"remaining_time":81.45933892},
{"learn":[0.04507846374],"iteration":552,"passed_time":100.5271225,"remaining_time":81.25790914},
{"learn":[0.04497616933],"iteration":553,"passed_time":100.6867307,"remaining_time":81.05827055},
{"learn":[0.0448416123],"iteration":554,"passed_time":100.8513165,"remaining_time":80.86276725},
{"learn":[0.0448131277],"iteration":555,"passed_time":101.0820278,"remaining_time":80.72018044},
{"learn":[0.04479396848],"iteration":556,"passed_time":101.2468724,"remaining_time":80.5248913},
{"learn":[0.04470389577],"iteration":557,"passed_time":101.4132228,"remaining_time":80.33090412},
{"learn":[0.04467384724],"iteration":558,"passed_time":101.5794041,"remaining_time":80.1368823},
{"learn":[0.04465456834],"iteration":559,"passed_time":101.7590144,"remaining_time":79.95351134},
{"learn":[0.04463506479],"iteration":560,"passed_time":101.9211587,"remaining_time":79.75648602},
{"learn":[0.04453649337],"iteration":561,"passed_time":102.0780161,"remaining_time":79.55546452},
{"learn":[0.04451760008],"iteration":562,"passed_time":102.2281279,"remaining_time":79.3493639},
{"learn":[0.04448833145],"iteration":563,"passed_time":102.377928,"remaining_time":79.14322096},
{"learn":[0.04442940813],"iteration":564,"passed_time":102.5386865,"remaining_time":78.94571438},
{"learn":[0.04427863405],"iteration":565,"passed_time":102.6921191,"remaining_time":78.74272032},
{"learn":[0.04425981182],"iteration":566,"passed_time":102.8531106,"remaining_time":78.54567355},
{"learn":[0.04422926444],"iteration":567,"passed_time":103.0198818,"remaining_time":78.35314955},
{"learn":[0.04421105247],"iteration":568,"passed_time":103.1845753,"remaining_time":78.15914226},
{"learn":[0.04418529226],"iteration":569,"passed_time":103.3498874,"remaining_time":77.96570456},
{"learn":[0.04413612943],"iteration":570,"passed_time":103.5052998,"remaining_time":77.76492755},
{"learn":[0.04410199936],"iteration":571,"passed_time":103.672325,"remaining_time":77.57299844},
{"learn":[0.04399460508],"iteration":572,"passed_time":103.8284789,"remaining_time":77.37305496},
{"learn":[0.0437655591],"iteration":573,"passed_time":104.0002398,"remaining_time":77.18484698},
{"learn":[0.04374673183],"iteration":574,"passed_time":104.1602854,"remaining_time":76.98803701},
{"learn":[0.0436970344],"iteration":575,"passed_time":104.3248051,"remaining_time":76.7946482},
{"learn":[0.04364706645],"iteration":576,"passed_time":104.4801555,"remaining_time":76.59463741},
{"learn":[0.04362921165],"iteration":577,"passed_time":104.6605667,"remaining_time":76.41307812},
{"learn":[0.04361071036],"iteration":578,"passed_time":104.8265223,"remaining_time":76.22101187},
{"learn":[0.04348319586],"iteration":579,"passed_time":104.9837278,"remaining_time":76.02269945},
{"learn":[0.04346450338],"iteration":580,"passed_time":105.1358276,"remaining_time":75.82084639},
{"learn":[0.04337062331],"iteration":581,"passed_time":105.2808584,"remaining_time":75.61408727},
{"learn":[0.04331231346],"iteration":582,"passed_time":105.4405018,"remaining_time":75.41799189},
{"learn":[0.04329416844],"iteration":583,"passed_time":105.6280337,"remaining_time":75.24188705},
{"learn":[0.04327697846],"iteration":584,"passed_time":105.7794583,"remaining_time":75.04012851},
{"learn":[0.04315884984],"iteration":585,"passed_time":105.942823,"remaining_time":74.84697733},
{"learn":[0.04304280281],"iteration":586,"passed_time":106.1101449,"remaining_time":74.65671185},
{"learn":[0.04302441661],"iteration":587,"passed_time":106.2861864,"remaining_time":74.47263402},
{"learn":[0.04287194701],"iteration":588,"passed_time":106.4518305,"remaining_time":74.28132825},
{"learn":[0.04277695876],"iteration":589,"passed_time":106.6115368,"remaining_time":74.08598323},
{"learn":[0.04275943637],"iteration":590,"passed_time":106.776141,"remaining_time":73.89414831},
{"learn":[0.04266948333],"iteration":591,"passed_time":107.0123663,"remaining_time":73.75176594},
{"learn":[0.04247601399],"iteration":592,"passed_time":107.2196541,"remaining_time":73.58920609},
{"learn":[0.04231503331],"iteration":593,"passed_time":107.4332991,"remaining_time":73.43084079},
{"learn":[0.04229748249],"iteration":594,"passed_time":107.6332116,"remaining_time":73.26294234},
{"learn":[0.04222840667],"iteration":595,"passed_time":107.8254739,"remaining_time":73.08975075},
{"learn":[0.04221108556],"iteration":596,"passed_time":108.0104565,"remaining_time":72.91158122},
{"learn":[0.04212149519],"iteration":597,"passed_time":108.2316161,"remaining_time":72.75770851},
{"learn":[0.04209213257],"iteration":598,"passed_time":108.4247154,"remaining_time":72.58482619},
{"learn":[0.0419806164],"iteration":599,"passed_time":108.6412059,"remaining_time":72.42747061},
{"learn":[0.04188975967],"iteration":600,"passed_time":108.8578156,"remaining_time":72.26999739},
{"learn":[0.04187278289],"iteration":601,"passed_time":109.0518434,"remaining_time":72.09739813},
{"learn":[0.04185525958],"iteration":602,"passed_time":109.2516262,"remaining_time":71.92851674},
{"learn":[0.04182780568],"iteration":603,"passed_time":109.4319349,"remaining_time":71.74676525},
{"learn":[0.04167107114],"iteration":604,"passed_time":109.6160427,"remaining_time":71.56749898},
{"learn":[0.0416537725],"iteration":605,"passed_time":109.7741731,"remaining_time":71.37132708},
{"learn":[0.04157234843],"iteration":606,"passed_time":109.9325379,"remaining_time":71.17543228},
{"learn":[0.04153492542],"iteration":607,"passed_time":110.0989901,"remaining_time":70.98487517},
{"learn":[0.04150939675],"iteration":608,"passed_time":110.2572699,"remaining_time":70.78915029},
{"learn":[0.04149223429],"iteration":609,"passed_time":110.43156,"remaining_time":70.60378428},
{"learn":[0.04133766935],"iteration":610,"passed_time":110.6136605,"remaining_time":70.42342708},
{"learn":[0.041217102],"iteration":611,"passed_time":110.7776677,"remaining_time":70.23159322},
{"learn":[0.04119977768],"iteration":612,"passed_time":110.9567836,"remaining_time":70.04938867},
{"learn":[0.04118358585],"iteration":613,"passed_time":111.1360127,"remaining_time":69.86726529},
{"learn":[0.0411544511],"iteration":614,"passed_time":111.3235977,"remaining_time":69.69038233},
{"learn":[0.04112760883],"iteration":615,"passed_time":111.4933294,"remaining_time":69.50233518},
{"learn":[0.04106042339],"iteration":616,"passed_time":111.6657148,"remaining_time":69.31599475},
{"learn":[0.0410445924],"iteration":617,"passed_time":111.828577,"remaining_time":69.12381297},
{"learn":[0.04094316501],"iteration":618,"passed_time":111.9831642,"remaining_time":68.9266326},
{"learn":[0.04092690624],"iteration":619,"passed_time":112.1443605,"remaining_time":68.7336403},
{"learn":[0.04091063509],"iteration":620,"passed_time":112.3264569,"remaining_time":68.55350592},
{"learn":[0.04087161789],"iteration":621,"passed_time":112.4884941,"remaining_time":68.36117488},
{"learn":[0.04073921259],"iteration":622,"passed_time":112.6654322,"remaining_time":68.17795819},
{"learn":[0.04072347925],"iteration":623,"passed_time":112.8226605,"remaining_time":67.98288514},
{"learn":[0.04070731997],"iteration":624,"passed_time":112.9848342,"remaining_time":67.79090055},
{"learn":[0.04060446024],"iteration":625,"passed_time":113.1526887,"remaining_time":67.60240509},
{"learn":[0.04058892039],"iteration":626,"passed_time":113.3689185,"remaining_time":67.44275375},
{"learn":[0.04053550408],"iteration":627,"passed_time":113.5502021,"remaining_time":67.26222165},
{"learn":[0.04050655686],"iteration":628,"passed_time":113.7313003,"remaining_time":67.08157774},
{"learn":[0.04044492749],"iteration":629,"passed_time":113.8983424,"remaining_time":66.89267728},
{"learn":[0.04021451015],"iteration":630,"passed_time":114.098795,"remaining_time":66.7233841},
{"learn":[0.04019885384],"iteration":631,"passed_time":114.3505878,"remaining_time":66.58388655},
{"learn":[0.04018336535],"iteration":632,"passed_time":114.5665857,"remaining_time":66.42328111},
{"learn":[0.04016732207],"iteration":633,"passed_time":114.7583936,"remaining_time":66.24853635},
{"learn":[0.04013581872],"iteration":634,"passed_time":114.9454752,"remaining_time":66.07102118},
{"learn":[0.04012006109],"iteration":635,"passed_time":115.129638,"remaining_time":65.89180539},
{"learn":[0.04010535295],"iteration":636,"passed_time":115.331199,"remaining_time":65.72248861},
{"learn":[0.03998666681],"iteration":637,"passed_time":115.5161158,"remaining_time":65.54362685},
{"learn":[0.03996091806],"iteration":638,"passed_time":115.6680268,"remaining_time":65.34609966},
{"learn":[0.03980147426],"iteration":639,"passed_time":115.8164071,"remaining_time":65.14672901},
{"learn":[0.03978561713],"iteration":640,"passed_time":115.9830821,"remaining_time":64.95776359},
{"learn":[0.03977067975],"iteration":641,"passed_time":116.164635,"remaining_time":64.77716404},
{"learn":[0.03970941351],"iteration":642,"passed_time":116.3312798,"remaining_time":64.58828442},
{"learn":[0.03969341241],"iteration":643,"passed_time":116.504483,"remaining_time":64.40309932},
{"learn":[0.03961963333],"iteration":644,"passed_time":116.6713402,"remaining_time":64.21445855},
{"learn":[0.03955023472],"iteration":645,"passed_time":116.8568995,"remaining_time":64.0361338},
{"learn":[0.03936819709],"iteration":646,"passed_time":117.0387861,"remaining_time":63.85578281},
{"learn":[0.03935329731],"iteration":647,"passed_time":117.268146,"remaining_time":63.70121514},
{"learn":[0.03932284759],"iteration":648,"passed_time":117.530627,"remaining_time":63.56432987},
{"learn":[0.03930771718],"iteration":649,"passed_time":117.7512212,"remaining_time":63.40450375},
{"learn":[0.03921274314],"iteration":650,"passed_time":117.9498542,"remaining_time":63.23271752},
{"learn":[0.03914864017],"iteration":651,"passed_time":118.1644493,"remaining_time":63.06936863},
{"learn":[0.03906641648],"iteration":652,"passed_time":118.3506381,"remaining_time":62.89076787},
{"learn":[0.03900526395],"iteration":653,"passed_time":118.6101774,"remaining_time":62.75095013},
{"learn":[0.03898838438],"iteration":654,"passed_time":118.7855106,"remaining_time":62.56641398},
{"learn":[0.03897275191],"iteration":655,"passed_time":118.9564267,"remaining_time":62.37958959},
{"learn":[0.03895367476],"iteration":656,"passed_time":119.1283923,"remaining_time":62.19336157},
{"learn":[0.03893604279],"iteration":657,"passed_time":119.3151061,"remaining_time":62.01484239},
{"learn":[0.03892012468],"iteration":658,"passed_time":119.4866615,"remaining_time":61.8284546},
{"learn":[0.03890338311],"iteration":659,"passed_time":119.7021938,"remaining_time":61.66476652},
{"learn":[0.03888759109],"iteration":660,"passed_time":119.9174007,"remaining_time":61.50075469},
{"learn":[0.03878979087],"iteration":661,"passed_time":120.1281653,"remaining_time":61.33432005},
{"learn":[0.03877439407],"iteration":662,"passed_time":120.3319657,"remaining_time":61.16421184},
{"learn":[0.03875707296],"iteration":663,"passed_time":120.5418703,"remaining_time":60.99709101},
{"learn":[0.03874040063],"iteration":664,"passed_time":120.7441239,"remaining_time":60.82598725},
{"learn":[0.03860618151],"iteration":665,"passed_time":120.940918,"remaining_time":60.65205199},
{"learn":[0.03858985717],"iteration":666,"passed_time":121.1232493,"remaining_time":60.47082762},
{"learn":[0.03854373785],"iteration":667,"passed_time":121.2989015,"remaining_time":60.2862804},
{"learn":[0.03852530901],"iteration":668,"passed_time":121.4632633,"remaining_time":60.09617361},
{"learn":[0.03850972011],"iteration":669,"passed_time":121.620895,"remaining_time":59.90282886},
{"learn":[0.03848284437],"iteration":670,"passed_time":121.8496183,"remaining_time":59.74444773},
{"learn":[0.03846356915],"iteration":671,"passed_time":122.0584955,"remaining_time":59.57617042},
{"learn":[0.03844890503],"iteration":672,"passed_time":122.2684921,"remaining_time":59.40831636},
{"learn":[0.03843132762],"iteration":673,"passed_time":122.4638145,"remaining_time":59.23323964},
{"learn":[0.038405699],"iteration":674,"passed_time":122.6583018,"remaining_time":59.05770088},
{"learn":[0.0383890693],"iteration":675,"passed_time":122.8481319,"remaining_time":58.87987386},
{"learn":[0.03837311864],"iteration":676,"passed_time":123.0740682,"remaining_time":58.71923787},
{"learn":[0.03835704969],"iteration":677,"passed_time":123.2870924,"remaining_time":58.55227693},
{"learn":[0.0383427895],"iteration":678,"passed_time":123.5852072,"remaining_time":58.42540725},
{"learn":[0.03832697639],"iteration":679,"passed_time":123.7803282,"remaining_time":58.24956623},
{"learn":[0.03830905465],"iteration":680,"passed_time":123.975777,"remaining_time":58.07382212},
{"learn":[0.03825827975],"iteration":681,"passed_time":124.1649744,"remaining_time":57.89510537},
{"learn":[0.03824323416],"iteration":682,"passed_time":124.3797961,"remaining_time":57.7282509},
{"learn":[0.0381039702],"iteration":683,"passed_time":124.5873679,"remaining_time":57.55790682},
{"learn":[0.03808956834],"iteration":684,"passed_time":124.778401,"remaining_time":57.37984865},
{"learn":[0.03795824464],"iteration":685,"passed_time":124.9620483,"remaining_time":57.19837197},
{"learn":[0.0379421147],"iteration":686,"passed_time":125.1417937,"remaining_time":57.01511124},
{"learn":[0.03792760372],"iteration":687,"passed_time":125.3097979,"remaining_time":56.82653624},
{"learn":[0.03784393072],"iteration":688,"passed_time":125.5003283,"remaining_time":56.64818885},
{"learn":[0.03776029669],"iteration":689,"passed_time":125.6669274,"remaining_time":56.45905434},
{"learn":[0.03774498472],"iteration":690,"passed_time":125.8155047,"remaining_time":56.26192612},
{"learn":[0.03772063301],"iteration":691,"passed_time":125.9702319,"remaining_time":56.06767547},
{"learn":[0.03770544987],"iteration":692,"passed_time":126.1732762,"remaining_time":55.89494342},
{"learn":[0.03769051662],"iteration":693,"passed_time":126.3940814,"remaining_time":55.7299552},
{"learn":[0.03763433282],"iteration":694,"passed_time":126.5774334,"remaining_time":55.54837005},
{"learn":[0.03761904469],"iteration":695,"passed_time":126.748136,"remaining_time":55.36125481},
{"learn":[0.03755910259],"iteration":696,"passed_time":126.9145261,"remaining_time":55.17231193},
{"learn":[0.03748337902],"iteration":697,"passed_time":127.0945465,"remaining_time":54.989331},
{"learn":[0.03746941135],"iteration":698,"passed_time":127.2645638,"remaining_time":54.80205107},
{"learn":[0.03745467938],"iteration":699,"passed_time":127.4587366,"remaining_time":54.62517282},
{"learn":[0.03743989513],"iteration":700,"passed_time":127.6606219,"remaining_time":54.45153487},
{"learn":[0.03742543092],"iteration":701,"passed_time":127.8568175,"remaining_time":54.27540115},
{"learn":[0.03741156688],"iteration":702,"passed_time":128.0369345,"remaining_time":54.09241756},
{"learn":[0.0372931673],"iteration":703,"passed_time":128.2226164,"remaining_time":53.91178191},
{"learn":[0.03727687597],"iteration":704,"passed_time":128.3750863,"remaining_time":53.71723471},
{"learn":[0.03726267906],"iteration":705,"passed_time":128.6275242,"remaining_time":53.56443644},
{"learn":[0.03724915798],"iteration":706,"passed_time":128.808572,"remaining_time":53.38177031},
{"learn":[0.03723494319],"iteration":707,"passed_time":128.9726563,"remaining_time":53.19211249},
{"learn":[0.03722156653],"iteration":708,"passed_time":129.1520913,"remaining_time":53.00882731},
{"learn":[0.03709194889],"iteration":709,"passed_time":129.3416633,"remaining_time":52.82969348},
{"learn":[0.03707826825],"iteration":710,"passed_time":129.5091727,"remaining_time":52.64156247},
{"learn":[0.0370540165],"iteration":711,"passed_time":129.7402048,"remaining_time":52.47918397},
{"learn":[0.03702761485],"iteration":712,"passed_time":129.9447891,"remaining_time":52.30596702},
{"learn":[0.03683842237],"iteration":713,"passed_time":130.1483746,"remaining_time":52.1322621},
{"learn":[0.03682319751],"iteration":714,"passed_time":130.3325598,"remaining_time":51.9507406},
{"learn":[0.03676554377],"iteration":715,"passed_time":130.5408678,"remaining_time":51.77877995},
{"learn":[0.03675286128],"iteration":716,"passed_time":130.7320834,"remaining_time":51.59997156},
{"learn":[0.03668612288],"iteration":717,"passed_time":130.9250286,"remaining_time":51.4218079},
{"learn":[0.03667404193],"iteration":718,"passed_time":131.1031646,"remaining_time":51.23781539},
{"learn":[0.03661048779],"iteration":719,"passed_time":131.2817895,"remaining_time":51.05402926},
{"learn":[0.03659548714],"iteration":720,"passed_time":131.4554608,"remaining_time":50.86834059},
{"learn":[0.03651690208],"iteration":721,"passed_time":131.6223046,"remaining_time":50.68005633},
{"learn":[0.03650487845],"iteration":722,"passed_time":131.7971066,"remaining_time":50.4948804},
{"learn":[0.03645175099],"iteration":723,"passed_time":131.9995704,"remaining_time":50.32027822},
{"learn":[0.03633207816],"iteration":724,"passed_time":132.2089673,"remaining_time":50.14822898},
{"learn":[0.03631740396],"iteration":725,"passed_time":132.3942743,"remaining_time":49.96698505},
{"learn":[0.03614356334],"iteration":726,"passed_time":132.5919989,"remaining_time":49.79039298},
{"learn":[0.03612916653],"iteration":727,"passed_time":132.7976354,"remaining_time":49.61669893},
{"learn":[0.03605514627],"iteration":728,"passed_time":133.1497402,"remaining_time":49.4973657},
{"learn":[0.03603133834],"iteration":729,"passed_time":133.3588788,"remaining_time":49.32451683},
{"learn":[0.03600598574],"iteration":730,"passed_time":133.5545679,"remaining_time":49.14661937},
{"learn":[0.03599098967],"iteration":731,"passed_time":133.7423211,"remaining_time":48.96576784},
{"learn":[0.03596987999],"iteration":732,"passed_time":133.9061491,"remaining_time":48.77618255},
{"learn":[0.0359562342],"iteration":733,"passed_time":134.1185961,"remaining_time":48.60428687},
{"learn":[0.03587435163],"iteration":734,"passed_time":134.3059894,"remaining_time":48.42324788},
{"learn":[0.03584558597],"iteration":735,"passed_time":134.4961296,"remaining_time":48.24317694},
{"learn":[0.03583136659],"iteration":736,"passed_time":134.6773043,"remaining_time":48.05987928},
{"learn":[0.03572855546],"iteration":737,"passed_time":134.8765886,"remaining_time":47.88301655},
{"learn":[0.03561658172],"iteration":738,"passed_time":135.0640491,"remaining_time":47.70191721},
{"learn":[0.03560440907],"iteration":739,"passed_time":135.239013,"remaining_time":47.51640998},
{"learn":[0.03559095309],"iteration":740,"passed_time":135.4164692,"remaining_time":47.33180234},
{"learn":[0.03554048126],"iteration":741,"passed_time":135.5909275,"remaining_time":47.14617157},
{"learn":[0.03548143139],"iteration":742,"passed_time":135.7600982,"remaining_time":46.95874191},
{"learn":[0.03545987377],"iteration":743,"passed_time":135.9234045,"remaining_time":46.76934347},
{"learn":[0.03544817888],"iteration":744,"passed_time":136.090791,"remaining_time":46.5814117},
{"learn":[0.03543429237],"iteration":745,"passed_time":136.2555186,"remaining_time":46.39262967},
{"learn":[0.03541337985],"iteration":746,"passed_time":136.4447806,"remaining_time":46.21222154},
{"learn":[0.03539987527],"iteration":747,"passed_time":136.6192746,"remaining_time":46.02681443},
{"learn":[0.03529637273],"iteration":748,"passed_time":136.7828936,"remaining_time":45.8377921},
{"learn":[0.03528349858],"iteration":749,"passed_time":136.9446537,"remaining_time":45.64821789},
{"learn":[0.03527006644],"iteration":750,"passed_time":137.0971712,"remaining_time":45.45565329},
{"learn":[0.03524150986],"iteration":751,"passed_time":137.2547918,"remaining_time":45.26487814},
{"learn":[0.03518912471],"iteration":752,"passed_time":137.4245633,"remaining_time":45.0781768},
{"learn":[0.03508974543],"iteration":753,"passed_time":137.5881315,"remaining_time":44.88949647},
{"learn":[0.03507679013],"iteration":754,"passed_time":137.7624265,"remaining_time":44.70436357},
{"learn":[0.03501782601],"iteration":755,"passed_time":138.0084219,"remaining_time":44.54240072},
{"learn":[0.03500473591],"iteration":756,"passed_time":138.1952258,"remaining_time":44.36121515},
{"learn":[0.03493186006],"iteration":757,"passed_time":138.3688922,"remaining_time":44.17582048},
{"learn":[0.03491284389],"iteration":758,"passed_time":138.5318293,"remaining_time":43.9870499},
{"learn":[0.03480967421],"iteration":759,"passed_time":138.7114451,"remaining_time":43.80361424},
{"learn":[0.03479128021],"iteration":760,"passed_time":138.886569,"remaining_time":43.61877792},
{"learn":[0.03478044271],"iteration":761,"passed_time":139.0781552,"remaining_time":43.43910884},
{"learn":[0.03476759058],"iteration":762,"passed_time":139.2496169,"remaining_time":43.25315754},
{"learn":[0.03475519327],"iteration":763,"passed_time":139.4132842,"remaining_time":43.06483648},
{"learn":[0.03474320173],"iteration":764,"passed_time":139.5873741,"remaining_time":42.8797816},
{"learn":[0.03470070454],"iteration":765,"passed_time":139.7459361,"remaining_time":42.69001181},
{"learn":[0.03468874326],"iteration":766,"passed_time":139.9060563,"remaining_time":42.50079676},
{"learn":[0.03467652889],"iteration":767,"passed_time":140.1099314,"remaining_time":42.3248751},
{"learn":[0.03466509718],"iteration":768,"passed_time":140.3464848,"remaining_time":42.15869701},
{"learn":[0.03465093787],"iteration":769,"passed_time":140.5343695,"remaining_time":41.97779867},
{"learn":[0.03463909305],"iteration":770,"passed_time":140.7325794,"remaining_time":41.79994902},
{"learn":[0.03462708271],"iteration":771,"passed_time":140.9932478,"remaining_time":41.64049287},
{"learn":[0.03461623513],"iteration":772,"passed_time":141.2415198,"remaining_time":41.47713452},
{"learn":[0.03460457554],"iteration":773,"passed_time":141.4359517,"remaining_time":41.29783604},
{"learn":[0.03459338546],"iteration":774,"passed_time":141.625654,"remaining_time":41.11712536},
{"learn":[0.03458098723],"iteration":775,"passed_time":141.8039423,"remaining_time":40.93309675},
{"learn":[0.0345698563],"iteration":776,"passed_time":142.0127128,"remaining_time":40.75783136},
{"learn":[0.0345593778],"iteration":777,"passed_time":142.2109454,"remaining_time":40.57947285},
{"learn":[0.03454843484],"iteration":778,"passed_time":142.4136654,"remaining_time":40.4023364},
{"learn":[0.03453756204],"iteration":779,"passed_time":142.5936345,"remaining_time":40.21871742},
{"learn":[0.03452694462],"iteration":780,"passed_time":142.8662062,"remaining_time":40.06107446},
{"learn":[0.0345150622],"iteration":781,"passed_time":143.0539923,"remaining_time":39.87950168},
{"learn":[0.03446830649],"iteration":782,"passed_time":143.2388755,"remaining_time":39.69710853},
{"learn":[0.03445789493],"iteration":783,"passed_time":143.393878,"remaining_time":39.5064766},
{"learn":[0.03444717481],"iteration":784,"passed_time":143.5729433,"remaining_time":39.32252588},
{"learn":[0.03443533686],"iteration":785,"passed_time":143.7491993,"remaining_time":39.1378227},
{"learn":[0.03431219321],"iteration":786,"passed_time":143.9247183,"remaining_time":38.95294156},
{"learn":[0.03429203675],"iteration":787,"passed_time":144.1034864,"remaining_time":38.76895827},
{"learn":[0.0341901715],"iteration":788,"passed_time":144.2702052,"remaining_time":38.58176591},
{"learn":[0.03415478743],"iteration":789,"passed_time":144.444781,"remaining_time":38.39671395},
{"learn":[0.03414448087],"iteration":790,"passed_time":144.6279605,"remaining_time":38.21396175},
{"learn":[0.03412622809],"iteration":791,"passed_time":144.841974,"remaining_time":38.03930629},
{"learn":[0.03411575006],"iteration":792,"passed_time":145.0134026,"remaining_time":37.85343547},
{"learn":[0.03404585261],"iteration":793,"passed_time":145.1783759,"remaining_time":37.66592624},
{"learn":[0.03398947853],"iteration":794,"passed_time":145.3394776,"remaining_time":37.47747535},
{"learn":[0.0339770042],"iteration":795,"passed_time":145.4946792,"remaining_time":37.28758111},
{"learn":[0.03390364647],"iteration":796,"passed_time":145.6466971,"remaining_time":37.096963},
{"learn":[0.03389286628],"iteration":797,"passed_time":145.8075976,"remaining_time":36.90869011},
{"learn":[0.03387869092],"iteration":798,"passed_time":145.9733793,"remaining_time":36.72171369},
{"learn":[0.03370058216],"iteration":799,"passed_time":146.1113071,"remaining_time":36.52782678},
{"learn":[0.03361029762],"iteration":800,"passed_time":146.2715221,"remaining_time":36.33961661},
{"learn":[0.03358006432],"iteration":801,"passed_time":146.4331272,"remaining_time":36.15181944},
{"learn":[0.03356834719],"iteration":802,"passed_time":146.596976,"remaining_time":35.96463795},
{"learn":[0.03355693404],"iteration":803,"passed_time":146.759436,"remaining_time":35.77717594},
{"learn":[0.03348522645],"iteration":804,"passed_time":146.9137436,"remaining_time":35.58780125},
{"learn":[0.03347442265],"iteration":805,"passed_time":147.0654669,"remaining_time":35.39789155},
{"learn":[0.03345738305],"iteration":806,"passed_time":147.2274892,"remaining_time":35.21053955},
{"learn":[0.03344651942],"iteration":807,"passed_time":147.4531036,"remaining_time":35.03836124},
{"learn":[0.0333395919],"iteration":808,"passed_time":147.6353156,"remaining_time":34.8558038},
{"learn":[0.03332736997],"iteration":809,"passed_time":147.8136656,"remaining_time":34.67234131},
{"learn":[0.03330950645],"iteration":810,"passed_time":147.9843988,"remaining_time":34.48711638},
{"learn":[0.03329759928],"iteration":811,"passed_time":148.141899,"remaining_time":34.29886332},
{"learn":[0.0332845399],"iteration":812,"passed_time":148.3064089,"remaining_time":34.11229824},
{"learn":[0.0332398112],"iteration":813,"passed_time":148.4634178,"remaining_time":33.92407335},
{"learn":[0.03322935219],"iteration":814,"passed_time":148.6243111,"remaining_time":33.73680682},
{"learn":[0.0331981283],"iteration":815,"passed_time":148.7799668,"remaining_time":33.54842388},
{"learn":[0.03313717911],"iteration":816,"passed_time":148.926504,"remaining_time":33.35807861},
{"learn":[0.03306771998],"iteration":817,"passed_time":149.1037025,"remaining_time":33.17466242},
{"learn":[0.03298954368],"iteration":818,"passed_time":149.260231,"remaining_time":32.98669329},
{"learn":[0.0329328012],"iteration":819,"passed_time":149.4253771,"remaining_time":32.80069254},
{"learn":[0.03291986676],"iteration":820,"passed_time":149.5795515,"remaining_time":32.61235045},
{"learn":[0.032908013],"iteration":821,"passed_time":149.731587,"remaining_time":32.42362833},
{"learn":[0.03286019243],"iteration":822,"passed_time":149.8901641,"remaining_time":32.23640225},
{"learn":[0.03284822863],"iteration":823,"passed_time":150.0611461,"remaining_time":32.05189528},
{"learn":[0.03277075016],"iteration":824,"passed_time":150.2125472,"remaining_time":31.86326759},
{"learn":[0.03275911877],"iteration":825,"passed_time":150.3718344,"remaining_time":31.67639127},
{"learn":[0.03270126169],"iteration":826,"passed_time":150.5424832,"remaining_time":31.49195839},
{"learn":[0.03263301872],"iteration":827,"passed_time":150.7145213,"remaining_time":31.30784742},
{"learn":[0.03255689098],"iteration":828,"passed_time":150.8733114,"remaining_time":31.12103288},
{"learn":[0.03254221953],"iteration":829,"passed_time":151.032608,"remaining_time":30.93438959},
{"learn":[0.03252475514],"iteration":830,"passed_time":151.1767538,"remaining_time":30.74473091},
{"learn":[0.03236975188],"iteration":831,"passed_time":151.3407396,"remaining_time":30.55918781},
{"learn":[0.03235202294],"iteration":832,"passed_time":151.5033368,"remaining_time":30.37341807},
{"learn":[0.03219199043],"iteration":833,"passed_time":151.7227485,"remaining_time":30.19901228},
{"learn":[0.03218183838],"iteration":834,"passed_time":151.8962422,"remaining_time":30.01542511},
{"learn":[0.03217122073],"iteration":835,"passed_time":152.0730948,"remaining_time":29.832521},
{"learn":[0.03215944515],"iteration":836,"passed_time":152.2444011,"remaining_time":29.64855124},
{"learn":[0.03214868468],"iteration":837,"passed_time":152.4187948,"remaining_time":29.46520853},
{"learn":[0.03206140857],"iteration":838,"passed_time":152.5846036,"remaining_time":29.28023979},
{"learn":[0.03196616975],"iteration":839,"passed_time":152.7657815,"remaining_time":29.0982441},
{"learn":[0.03195095269],"iteration":840,"passed_time":152.9508528,"remaining_time":28.91698644},
{"learn":[0.03193785915],"iteration":841,"passed_time":153.1157339,"remaining_time":28.73193107},
{"learn":[0.03191620157],"iteration":842,"passed_time":153.2808759,"remaining_time":28.54697213},
{"learn":[0.03190322427],"iteration":843,"passed_time":153.468376,"remaining_time":28.36619273},
{"learn":[0.03187851195],"iteration":844,"passed_time":153.6397813,"remaining_time":28.18244509},
{"learn":[0.03186642],"iteration":845,"passed_time":153.8135006,"remaining_time":27.99914786},
{"learn":[0.03185399633],"iteration":846,"passed_time":153.9729978,"remaining_time":27.81330421},
{"learn":[0.0318423732],"iteration":847,"passed_time":154.1207414,"remaining_time":27.62541591},
{"learn":[0.03176129185],"iteration":848,"passed_time":154.2920129,"remaining_time":27.44180678},
{"learn":[0.03168111398],"iteration":849,"passed_time":154.4765764,"remaining_time":27.26057231},
{"learn":[0.03165760636],"iteration":850,"passed_time":154.6518574,"remaining_time":27.07770476},
{"learn":[0.03164540621],"iteration":851,"passed_time":154.8262651,"remaining_time":26.89470334},
{"learn":[0.03161965035],"iteration":852,"passed_time":154.981806,"remaining_time":26.70847068},
{"learn":[0.03160901345],"iteration":853,"passed_time":155.1543499,"remaining_time":26.52521673},
{"learn":[0.0315971629],"iteration":854,"passed_time":155.3179186,"remaining_time":26.34046574},
{"learn":[0.03155662417],"iteration":855,"passed_time":155.4623095,"remaining_time":26.15253804},
{"learn":[0.03151200758],"iteration":856,"passed_time":155.6330033,"remaining_time":25.9691009},
{"learn":[0.03149824968],"iteration":857,"passed_time":155.8531667,"remaining_time":25.79388073},
{"learn":[0.03138208298],"iteration":858,"passed_time":156.057455,"remaining_time":25.61595012},
{"learn":[0.03136556653],"iteration":859,"passed_time":156.3419039,"remaining_time":25.45100761},
{"learn":[0.03135420382],"iteration":860,"passed_time":156.5391888,"remaining_time":25.27171572},
{"learn":[0.03134222673],"iteration":861,"passed_time":156.710725,"remaining_time":25.08825991},
{"learn":[0.03133084957],"iteration":862,"passed_time":156.8820216,"remaining_time":24.90479369},
{"learn":[0.031319234],"iteration":863,"passed_time":157.0503082,"remaining_time":24.72088185},
{"learn":[0.03130841209],"iteration":864,"passed_time":157.2031005,"remaining_time":24.53458794},
{"learn":[0.03124554226],"iteration":865,"passed_time":157.3754024,"remaining_time":24.35139022},
{"learn":[0.03123383958],"iteration":866,"passed_time":157.5409236,"remaining_time":24.16717744},
{"learn":[0.03122264032],"iteration":867,"passed_time":157.7078801,"remaining_time":23.98322601},
{"learn":[0.03121316433],"iteration":868,"passed_time":157.9038975,"remaining_time":23.80369456},
{"learn":[0.03120147746],"iteration":869,"passed_time":158.094765,"remaining_time":23.6233557},
{"learn":[0.03119212481],"iteration":870,"passed_time":158.2850076,"remaining_time":23.44290009},
{"learn":[0.03118115045],"iteration":871,"passed_time":158.4790095,"remaining_time":23.26297388},
{"learn":[0.03110371966],"iteration":872,"passed_time":158.6702304,"remaining_time":23.08261084},
{"learn":[0.03109214168],"iteration":873,"passed_time":158.8735904,"remaining_time":22.90397299},
{"learn":[0.03108122922],"iteration":874,"passed_time":159.048431,"remaining_time":22.72120443},
{"learn":[0.03106048543],"iteration":875,"passed_time":159.2189412,"remaining_time":22.53784099},
{"learn":[0.03097146291],"iteration":876,"passed_time":159.3900127,"remaining_time":22.35458559},
{"learn":[0.03096016072],"iteration":877,"passed_time":159.5478542,"remaining_time":22.1695196},
{"learn":[0.03083339586],"iteration":878,"passed_time":159.7077444,"remaining_time":21.98479758},
{"learn":[0.03076021006],"iteration":879,"passed_time":159.8775888,"remaining_time":21.80148938},
{"learn":[0.03074450355],"iteration":880,"passed_time":160.0448997,"remaining_time":21.61786953},
{"learn":[0.03072805313],"iteration":881,"passed_time":160.2251895,"remaining_time":21.43602309},
{"learn":[0.03066947644],"iteration":882,"passed_time":160.4001661,"remaining_time":21.25347615},
{"learn":[0.03066056371],"iteration":883,"passed_time":160.6475728,"remaining_time":21.08045073},
{"learn":[0.03064801601],"iteration":884,"passed_time":160.8278214,"remaining_time":20.89853046},
{"learn":[0.03061643312],"iteration":885,"passed_time":161.0036772,"remaining_time":20.71604876},
{"learn":[0.03052264544],"iteration":886,"passed_time":161.2025215,"remaining_time":20.53651064},
{"learn":[0.03051356857],"iteration":887,"passed_time":161.3552951,"remaining_time":20.3511183},
{"learn":[0.03049351619],"iteration":888,"passed_time":161.5263428,"remaining_time":20.16808105},
{"learn":[0.03039972988],"iteration":889,"passed_time":161.704102,"remaining_time":19.98590025},
{"learn":[0.03037575025],"iteration":890,"passed_time":161.8719106,"remaining_time":19.80251207},
{"learn":[0.03036510715],"iteration":891,"passed_time":162.0484763,"remaining_time":19.62021911},
{"learn":[0.03028216637],"iteration":892,"passed_time":162.2253751,"remaining_time":19.43797887},
{"learn":[0.03022648898],"iteration":893,"passed_time":162.4156315,"remaining_time":19.25733438},
{"learn":[0.03021590343],"iteration":894,"passed_time":162.5864266,"remaining_time":19.07438524},
{"learn":[0.03015913276],"iteration":895,"passed_time":162.7736888,"remaining_time":18.89337459},
{"learn":[0.03014382307],"iteration":896,"passed_time":162.963779,"remaining_time":18.71267474},
{"learn":[0.03007994592],"iteration":897,"passed_time":163.1923909,"remaining_time":18.53632948},
{"learn":[0.03006744133],"iteration":898,"passed_time":163.3912769,"remaining_time":18.35652833},
{"learn":[0.03005711941],"iteration":899,"passed_time":163.5610877,"remaining_time":18.17345419},
{"learn":[0.03004828233],"iteration":900,"passed_time":163.7103982,"remaining_time":17.98815696},
{"learn":[0.02999626788],"iteration":901,"passed_time":163.8743657,"remaining_time":17.80453197},
{"learn":[0.02998093802],"iteration":902,"passed_time":164.0327225,"remaining_time":17.62034782},
{"learn":[0.02991720002],"iteration":903,"passed_time":164.1897144,"remaining_time":17.43607586},
{"learn":[0.02990667591],"iteration":904,"passed_time":164.3530031,"remaining_time":17.25252518},
{"learn":[0.02989644225],"iteration":905,"passed_time":164.508379,"remaining_time":17.06819826},
{"learn":[0.02983235442],"iteration":906,"passed_time":164.6674399,"remaining_time":16.88431302},
{"learn":[0.0298221242],"iteration":907,"passed_time":164.8735121,"remaining_time":16.70524572},
{"learn":[0.02981139307],"iteration":908,"passed_time":165.0524179,"remaining_time":16.52339937},
{"learn":[0.02979919635],"iteration":909,"passed_time":165.2218793,"remaining_time":16.34062542},
{"learn":[0.02978877333],"iteration":910,"passed_time":165.3876159,"remaining_time":16.15751681},
{"learn":[0.02977880239],"iteration":911,"passed_time":165.5458933,"remaining_time":15.97372654},
{"learn":[0.02972163971],"iteration":912,"passed_time":165.6971492,"remaining_time":15.78932309},
{"learn":[0.02970867615],"iteration":913,"passed_time":165.8585161,"remaining_time":15.60594353},
{"learn":[0.02970025081],"iteration":914,"passed_time":166.0390302,"remaining_time":15.42439078},
{"learn":[0.02966990448],"iteration":915,"passed_time":166.2045231,"remaining_time":15.24146281},
{"learn":[0.02960090683],"iteration":916,"passed_time":166.3705654,"remaining_time":15.05862261},
{"learn":[0.02959215297],"iteration":917,"passed_time":166.5340549,"remaining_time":14.87559096},
{"learn":[0.0295487099],"iteration":918,"passed_time":166.6810607,"remaining_time":14.69114898},
{"learn":[0.02952805391],"iteration":919,"passed_time":166.8471315,"remaining_time":14.50844622},
{"learn":[0.02947867559],"iteration":920,"passed_time":167.0117049,"remaining_time":14.32565113},
{"learn":[0.0294679048],"iteration":921,"passed_time":167.1713135,"remaining_time":14.14247554},
{"learn":[0.02945906635],"iteration":922,"passed_time":167.3337461,"remaining_time":13.95958662},
{"learn":[0.02938450506],"iteration":923,"passed_time":167.4892609,"remaining_time":13.77617297},
{"learn":[0.02937572896],"iteration":924,"passed_time":167.6425575,"remaining_time":13.5926398},
{"learn":[0.02936749137],"iteration":925,"passed_time":167.8028764,"remaining_time":13.4097331},
{"learn":[0.02934629069],"iteration":926,"passed_time":167.9712288,"remaining_time":13.22750777},
{"learn":[0.02924572138],"iteration":927,"passed_time":168.1191579,"remaining_time":13.04372777},
{"learn":[0.02922621622],"iteration":928,"passed_time":168.2734446,"remaining_time":12.86051084},
{"learn":[0.02921665815],"iteration":929,"passed_time":168.4466517,"remaining_time":12.67878024},
{"learn":[0.02920817916],"iteration":930,"passed_time":168.5975169,"remaining_time":12.4954121},
{"learn":[0.02919208064],"iteration":931,"passed_time":168.8181476,"remaining_time":12.3172039},
{"learn":[0.02913553371],"iteration":932,"passed_time":168.9822429,"remaining_time":12.13484488},
{"learn":[0.02912463592],"iteration":933,"passed_time":169.1457385,"remaining_time":11.95248259},
{"learn":[0.02895332758],"iteration":934,"passed_time":169.3300512,"remaining_time":11.77160784},
{"learn":[0.02889614266],"iteration":935,"passed_time":169.5256126,"remaining_time":11.59149488},
{"learn":[0.02881524632],"iteration":936,"passed_time":169.694791,"remaining_time":11.40957507},
{"learn":[0.02880681799],"iteration":937,"passed_time":169.8762666,"remaining_time":11.22849523},
{"learn":[0.02879711619],"iteration":938,"passed_time":170.0261124,"remaining_time":11.0453598},
{"learn":[0.02878767894],"iteration":939,"passed_time":170.1900411,"remaining_time":10.86319411},
{"learn":[0.02875607564],"iteration":940,"passed_time":170.370215,"remaining_time":10.68208575},
{"learn":[0.02868651839],"iteration":941,"passed_time":170.553214,"remaining_time":10.5011533},
{"learn":[0.02867201292],"iteration":942,"passed_time":170.7437687,"remaining_time":10.32067319},
{"learn":[0.02865489607],"iteration":943,"passed_time":170.9118301,"remaining_time":10.13883738},
{"learn":[0.02864671877],"iteration":944,"passed_time":171.1011413,"remaining_time":9.958267486},
{"learn":[0.02863855912],"iteration":945,"passed_time":171.2946105,"remaining_time":9.777916454},
{"learn":[0.02855414473],"iteration":946,"passed_time":171.477321,"remaining_time":9.596935598},
{"learn":[0.02853953426],"iteration":947,"passed_time":171.6683975,"remaining_time":9.41640999},
{"learn":[0.02846837777],"iteration":948,"passed_time":171.8380182,"remaining_time":9.234709094},
{"learn":[0.02846016609],"iteration":949,"passed_time":172.0109115,"remaining_time":9.053205868},
{"learn":[0.02833932363],"iteration":950,"passed_time":172.177517,"remaining_time":8.871396773},
{"learn":[0.02833109338],"iteration":951,"passed_time":172.3410951,"remaining_time":8.689466982},
{"learn":[0.02825166354],"iteration":952,"passed_time":172.5079792,"remaining_time":8.507738742},
{"learn":[0.02819262743],"iteration":953,"passed_time":172.6832042,"remaining_time":8.326443809},
{"learn":[0.0281433486],"iteration":954,"passed_time":172.8461345,"remaining_time":8.144582253},
{"learn":[0.02813520363],"iteration":955,"passed_time":173.057637,"remaining_time":7.964995843},
{"learn":[0.02812698346],"iteration":956,"passed_time":173.2427539,"remaining_time":7.784157174},
{"learn":[0.02806125673],"iteration":957,"passed_time":173.420584,"remaining_time":7.602990112},
{"learn":[0.02801784162],"iteration":958,"passed_time":173.5844993,"remaining_time":7.421235109},
{"learn":[0.02800976038],"iteration":959,"passed_time":173.7563447,"remaining_time":7.239847698},
{"learn":[0.02792440538],"iteration":960,"passed_time":173.9219041,"remaining_time":7.058225038},
{"learn":[0.02791491128],"iteration":961,"passed_time":174.0912143,"remaining_time":6.876783935},
{"learn":[0.02789473602],"iteration":962,"passed_time":174.25032,"remaining_time":6.69497595},
{"learn":[0.02782429021],"iteration":963,"passed_time":174.4178697,"remaining_time":6.513530405},
{"learn":[0.02781518721],"iteration":964,"passed_time":174.5745677,"remaining_time":6.331720073},
{"learn":[0.02778930527],"iteration":965,"passed_time":174.7399653,"remaining_time":6.15026793},
{"learn":[0.02773570854],"iteration":966,"passed_time":174.8958483,"remaining_time":5.968524294},
{"learn":[0.0277273389],"iteration":967,"passed_time":175.0593681,"remaining_time":5.78708655},
{"learn":[0.0277194704],"iteration":968,"passed_time":175.2100615,"remaining_time":5.605275446},
{"learn":[0.02770770949],"iteration":969,"passed_time":175.3914444,"remaining_time":5.424477663},
{"learn":[0.02769959707],"iteration":970,"passed_time":175.5485299,"remaining_time":5.242953004},
{"learn":[0.0276879306],"iteration":971,"passed_time":175.7067787,"remaining_time":5.061512145},
{"learn":[0.02761095671],"iteration":972,"passed_time":175.8913099,"remaining_time":4.880848272},
{"learn":[0.02753092349],"iteration":973,"passed_time":176.0911051,"remaining_time":4.700583913},
{"learn":[0.02752304398],"iteration":974,"passed_time":176.2756855,"remaining_time":4.519889371},
{"learn":[0.02750868614],"iteration":975,"passed_time":176.4620078,"remaining_time":4.339229699},
{"learn":[0.02745776016],"iteration":976,"passed_time":176.6452702,"remaining_time":4.158486401},
{"learn":[0.02745000835],"iteration":977,"passed_time":176.8976059,"remaining_time":3.979291749},
{"learn":[0.02744231385],"iteration":978,"passed_time":177.0682861,"remaining_time":3.798196128},
{"learn":[0.02738600327],"iteration":979,"passed_time":177.2534494,"remaining_time":3.617417334},
{"learn":[0.02737859969],"iteration":980,"passed_time":177.4141309,"remaining_time":3.43615544},
{"learn":[0.02734571925],"iteration":981,"passed_time":177.5766487,"remaining_time":3.254969121},
{"learn":[0.02733624921],"iteration":982,"passed_time":177.7452246,"remaining_time":3.073925553},
{"learn":[0.0273276501],"iteration":983,"passed_time":177.928903,"remaining_time":2.893152895},
{"learn":[0.02729563255],"iteration":984,"passed_time":178.1068461,"remaining_time":2.712286997},
{"learn":[0.02728566619],"iteration":985,"passed_time":178.2823677,"remaining_time":2.531392645},
{"learn":[0.02720343058],"iteration":986,"passed_time":178.4520087,"remaining_time":2.350431726},
{"learn":[0.02719232119],"iteration":987,"passed_time":178.6640138,"remaining_time":2.170008265},
{"learn":[0.0271178688],"iteration":988,"passed_time":178.8989379,"remaining_time":1.989775851},
{"learn":[0.02704473803],"iteration":989,"passed_time":179.1114499,"remaining_time":1.809206565},
{"learn":[0.02703722486],"iteration":990,"passed_time":179.3155741,"remaining_time":1.628496636},
{"learn":[0.02697913486],"iteration":991,"passed_time":179.5045987,"remaining_time":1.447617731},
{"learn":[0.02697133101],"iteration":992,"passed_time":179.6894476,"remaining_time":1.266692984},
{"learn":[0.02696394554],"iteration":993,"passed_time":179.8841481,"remaining_time":1.085819807},
{"learn":[0.02688631117],"iteration":994,"passed_time":180.0880266,"remaining_time":0.9049649579},
{"learn":[0.02687886701],"iteration":995,"passed_time":180.2983678,"remaining_time":0.7240898306},
{"learn":[0.0268128065],"iteration":996,"passed_time":180.493578,"remaining_time":0.5431100642},
{"learn":[0.02680353522],"iteration":997,"passed_time":180.7616849,"remaining_time":0.3622478654},
{"learn":[0.02669606805],"iteration":998,"passed_time":180.9633082,"remaining_time":0.1811444526},
{"learn":[0.02665622005],"iteration":999,"passed_time":181.1559999,"remaining_time":0}
]}